{"version":3,"kind":"Notebook","sha256":"b9ff1e17988ab8a32f0f05d2beb3d763c5a04c96664c23ae54c58e3af756b5c6","slug":"notebooks.gdex-intro.gdex-intro","location":"/notebooks/gdex_intro/gdex_intro.ipynb","dependencies":[],"frontmatter":{"title":"Introduction to NSF NCAR’s Geoscience Data Exchange","content_includes_title":false,"kernelspec":{"name":"python3","display_name":"Python 3 (ipykernel)","language":"python"},"authors":[{"nameParsed":{"literal":"Harsha R. Hampapura","given":"Harsha R.","family":"Hampapura"},"name":"Harsha R. Hampapura","orcid":"0000-0002-2449-9032","affiliations":["ncar"],"github":"hrhampapura","id":"contributors-myst-generated-uid-0"},{"nameParsed":{"literal":"Riley P. Conroy","given":"Riley P.","family":"Conroy"},"name":"Riley P. Conroy","orcid":"0009-0002-6453-2412","affiliations":["ncar"],"github":"rpconroy","id":"contributors-myst-generated-uid-1"},{"nameParsed":{"literal":"Chia-Wei Hsu","given":"Chia-Wei","family":"Hsu"},"name":"Chia-Wei Hsu","orcid":"0000-0002-4838-0140","affiliations":["ncar"],"url":"https://github.com/ProjectPythia/gdex-cookbook/graphs/contributors","github":"chiaweh2","id":"contributors-myst-generated-uid-2"}],"open_access":true,"license":{"content":{"id":"CC-BY-4.0","url":"https://creativecommons.org/licenses/by/4.0/","name":"Creative Commons Attribution 4.0 International","free":true,"CC":true},"code":{"id":"Apache-2.0","url":"https://opensource.org/licenses/Apache-2.0","name":"Apache License 2.0","free":true,"osi":true}},"github":"https://github.com/projectpythia/gdex-cookbook","copyright":"2026","affiliations":[{"id":"ncar","name":"NSF NCAR"},{"id":"UAlbany","name":"University at Albany (SUNY)","department":"Atmospheric and Environmental Sciences","url":"https://www.albany.edu/daes"},{"id":"CISL","name":"NSF National Center for Atmospheric Research","department":"Computational and Information Systems Lab","url":"https://www.cisl.ucar.edu"},{"id":"Unidata","name":"NSF Unidata","url":"https://www.unidata.ucar.edu"},{"id":"Argonne","name":"Argonne National Laboratory","department":"Environmental Science Division","url":"https://www.anl.gov/evs"},{"id":"CarbonPlan","name":"CarbonPlan","url":"https://carbonplan.org"},{"id":"NVIDIA","name":"NVIDIA Corporation","url":"https://www.nvidia.com/"}],"numbering":{"title":{"offset":1}},"source_url":"https://github.com/projectpythia/gdex-cookbook/blob/main/notebooks/gdex_intro/gdex_intro.ipynb","edit_url":"https://github.com/projectpythia/gdex-cookbook/edit/main/notebooks/gdex_intro/gdex_intro.ipynb","thumbnail":"/gdex-cookbook/build/gdex_logo-a1e621a85c35938e2de6d2579051229b.png","exports":[{"format":"ipynb","filename":"gdex_intro.ipynb","url":"/gdex-cookbook/build/gdex_intro-6a933f8dc6f4e7fddaf914a6999c8796.ipynb"}]},"widgets":{},"mdast":{"type":"root","children":[{"type":"block","kind":"notebook-content","children":[{"type":"container","kind":"figure","children":[{"type":"image","url":"/gdex-cookbook/build/gdex_logo-a1e621a85c35938e2de6d2579051229b.png","alt":"NSF NCAR GDEX logo","width":"300px","key":"ueBZ5h36Gb","urlSource":"../../thumbnails/gdex_logo.png"}],"enumerator":"1","key":"K4jS6W8qA1"}],"key":"lYHtC9k88t"},{"type":"block","kind":"notebook-content","children":[{"type":"thematicBreak","position":{"start":{"line":1,"column":1},"end":{"line":1,"column":1}},"key":"b1HAg0GRul"}],"key":"fVe7mEUHsQ"},{"type":"block","kind":"notebook-content","children":[{"type":"heading","depth":2,"position":{"start":{"line":1,"column":1},"end":{"line":1,"column":1}},"children":[{"type":"text","value":"Overview","position":{"start":{"line":1,"column":1},"end":{"line":1,"column":1}},"key":"B0xQvzS3sg"}],"identifier":"overview","label":"Overview","html_id":"overview","implicit":true,"key":"E1I3h6DtFl"},{"type":"paragraph","position":{"start":{"line":3,"column":1},"end":{"line":3,"column":1}},"children":[{"type":"text","value":"NSF NCAR’s ","position":{"start":{"line":3,"column":1},"end":{"line":3,"column":1}},"key":"pqkAQZeA7P"},{"type":"strong","position":{"start":{"line":3,"column":1},"end":{"line":3,"column":1}},"children":[{"type":"text","value":"Geoscience Data Exchange (GDEX)","position":{"start":{"line":3,"column":1},"end":{"line":3,"column":1}},"key":"GH8NewSy9q"}],"key":"tzzFdL1lrF"},{"type":"text","value":" is the long-term, trusted home for geoscience data at the ","position":{"start":{"line":3,"column":1},"end":{"line":3,"column":1}},"key":"wGoGPQJrTW"},{"type":"strong","position":{"start":{"line":3,"column":1},"end":{"line":3,"column":1}},"children":[{"type":"text","value":"National Center for Atmospheric Research (NCAR)","position":{"start":{"line":3,"column":1},"end":{"line":3,"column":1}},"key":"l0byLxenS0"}],"key":"UX3IzPTpXO"},{"type":"text","value":", funded by the ","position":{"start":{"line":3,"column":1},"end":{"line":3,"column":1}},"key":"XcpfKukNf0"},{"type":"strong","position":{"start":{"line":3,"column":1},"end":{"line":3,"column":1}},"children":[{"type":"text","value":"National Science Foundation (NSF)","position":{"start":{"line":3,"column":1},"end":{"line":3,"column":1}},"key":"mZ1gTyceqw"}],"key":"m7UHTPvHQn"},{"type":"text","value":". GDEX bridges the gap between data producers and the broader scientific community by providing curated, openly accessible datasets alongside the tools and services that can help enable scientific insight.","position":{"start":{"line":3,"column":1},"end":{"line":3,"column":1}},"key":"FKIqM9cDTn"}],"key":"EKkf4fUU82"},{"type":"paragraph","position":{"start":{"line":5,"column":1},"end":{"line":5,"column":1}},"children":[{"type":"text","value":"Whether you are looking to download terabytes of reanalysis data, stream a climate model output directly into a Python workflow, or archive your own research dataset with a citable DOI, GDEX is built to support the full lifecycle of geoscience data.","position":{"start":{"line":5,"column":1},"end":{"line":5,"column":1}},"key":"j3Zizutbvz"}],"key":"IaXFp7RjFE"},{"type":"paragraph","position":{"start":{"line":7,"column":1},"end":{"line":7,"column":1}},"children":[{"type":"text","value":"Visit GDEX at ","position":{"start":{"line":7,"column":1},"end":{"line":7,"column":1}},"key":"zBVarUtUJF"},{"type":"link","url":"https://gdex.ucar.edu","position":{"start":{"line":7,"column":1},"end":{"line":7,"column":1}},"children":[{"type":"text","value":"gdex.ucar.edu","position":{"start":{"line":7,"column":1},"end":{"line":7,"column":1}},"key":"deU4FkAGsl"}],"urlSource":"https://gdex.ucar.edu","key":"H2K1VSrdvn"}],"key":"ZbxOhelJgh"},{"type":"heading","depth":3,"position":{"start":{"line":9,"column":1},"end":{"line":9,"column":1}},"children":[{"type":"text","value":"In this Cookbook you will learn:","position":{"start":{"line":9,"column":1},"end":{"line":9,"column":1}},"key":"j5VHzr4VM0"}],"identifier":"in-this-cookbook-you-will-learn","label":"In this Cookbook you will learn:","html_id":"in-this-cookbook-you-will-learn","implicit":true,"key":"pGaCaD2otu"},{"type":"list","ordered":true,"start":1,"spread":false,"position":{"start":{"line":11,"column":1},"end":{"line":15,"column":1}},"children":[{"type":"listItem","spread":true,"position":{"start":{"line":11,"column":1},"end":{"line":11,"column":1}},"children":[{"type":"paragraph","children":[{"type":"text","value":"The mission and purpose of GDEX","position":{"start":{"line":11,"column":1},"end":{"line":11,"column":1}},"key":"fQ7SYrkwdD"}],"key":"noMKYUTGQV"}],"key":"mYWGTItZhI"},{"type":"listItem","spread":true,"position":{"start":{"line":12,"column":1},"end":{"line":12,"column":1}},"children":[{"type":"paragraph","children":[{"type":"text","value":"The breadth of data collections available","position":{"start":{"line":12,"column":1},"end":{"line":12,"column":1}},"key":"NNI0y5wr11"}],"key":"e5lnUhA60J"}],"key":"Cr6FIH7p7R"},{"type":"listItem","spread":true,"position":{"start":{"line":13,"column":1},"end":{"line":13,"column":1}},"children":[{"type":"paragraph","children":[{"type":"text","value":"Key services and tools for data access and analysis","position":{"start":{"line":13,"column":1},"end":{"line":13,"column":1}},"key":"v9xg2ScfGo"}],"key":"kq08ko55Hx"}],"key":"CqBFYtdHIE"},{"type":"listItem","spread":true,"position":{"start":{"line":14,"column":1},"end":{"line":14,"column":1}},"children":[{"type":"paragraph","children":[{"type":"text","value":"How to submit your own data to GDEX","position":{"start":{"line":14,"column":1},"end":{"line":14,"column":1}},"key":"Mx1acQ8KS6"}],"key":"POk84kHsVB"}],"key":"XAUoHXcY2E"},{"type":"listItem","spread":true,"position":{"start":{"line":15,"column":1},"end":{"line":15,"column":1}},"children":[{"type":"paragraph","children":[{"type":"text","value":"How GDEX enables reproducible, open science","position":{"start":{"line":15,"column":1},"end":{"line":15,"column":1}},"key":"QYGR1EIQvv"}],"key":"bqb2BxSSrh"}],"key":"FRzpbkGEUq"}],"key":"KK2PpiqiCP"}],"key":"OKOckvtvSi"},{"type":"block","kind":"notebook-content","children":[{"type":"thematicBreak","position":{"start":{"line":1,"column":1},"end":{"line":1,"column":1}},"key":"gXvjdu81CH"}],"key":"Kq7io0guW0"},{"type":"block","kind":"notebook-content","children":[{"type":"heading","depth":2,"position":{"start":{"line":1,"column":1},"end":{"line":1,"column":1}},"children":[{"type":"text","value":"Mission and Purpose","position":{"start":{"line":1,"column":1},"end":{"line":1,"column":1}},"key":"HllD6HhPV4"}],"identifier":"mission-and-purpose","label":"Mission and Purpose","html_id":"mission-and-purpose","implicit":true,"key":"hjXAfNvseO"},{"type":"paragraph","position":{"start":{"line":3,"column":1},"end":{"line":3,"column":1}},"children":[{"type":"text","value":"GDEX exists to  make geoscience data ","position":{"start":{"line":3,"column":1},"end":{"line":3,"column":1}},"key":"s68aH25dmK"},{"type":"strong","position":{"start":{"line":3,"column":1},"end":{"line":3,"column":1}},"children":[{"type":"text","value":"findable, accessible, interoperable, and reusable (FAIR)","position":{"start":{"line":3,"column":1},"end":{"line":3,"column":1}},"key":"XiTuJbLnok"}],"key":"aSn2qA1nFO"},{"type":"text","value":" to the NCAR scientists and the broader community.","position":{"start":{"line":3,"column":1},"end":{"line":3,"column":1}},"key":"MNSxl8JeHh"}],"key":"xDoPgocBLW"},{"type":"heading","depth":3,"position":{"start":{"line":5,"column":1},"end":{"line":5,"column":1}},"children":[{"type":"text","value":"Open Science","position":{"start":{"line":5,"column":1},"end":{"line":5,"column":1}},"key":"TE7S4LwS3S"}],"identifier":"open-science","label":"Open Science","html_id":"open-science","implicit":true,"key":"xiTFeHhKrr"},{"type":"paragraph","position":{"start":{"line":7,"column":1},"end":{"line":7,"column":1}},"children":[{"type":"text","value":"GDEX is committed to open science. Currently, all datasets are freely accessible to anyone, anywhere in the world without institutional or technical barriers. Additionally, data services are continuously being developed and expanded to minimize friction with obtaining and interacting with data.","position":{"start":{"line":7,"column":1},"end":{"line":7,"column":1}},"key":"dQVGgaJg6O"}],"key":"RRqrb2Q9VA"},{"type":"heading","depth":3,"position":{"start":{"line":9,"column":1},"end":{"line":9,"column":1}},"children":[{"type":"text","value":"Supporting the Full Data Lifecycle","position":{"start":{"line":9,"column":1},"end":{"line":9,"column":1}},"key":"YxmD2B43JW"}],"identifier":"supporting-the-full-data-lifecycle","label":"Supporting the Full Data Lifecycle","html_id":"supporting-the-full-data-lifecycle","implicit":true,"key":"tcvw7Dz7iG"},{"type":"paragraph","position":{"start":{"line":11,"column":1},"end":{"line":11,"column":1}},"children":[{"type":"text","value":"GDEX supports data from initial archival through active use in research workflows:","position":{"start":{"line":11,"column":1},"end":{"line":11,"column":1}},"key":"mD9y6BhXqY"}],"key":"IbsmqAieIB"},{"type":"list","ordered":false,"spread":false,"position":{"start":{"line":13,"column":1},"end":{"line":18,"column":1}},"children":[{"type":"listItem","spread":true,"position":{"start":{"line":13,"column":1},"end":{"line":13,"column":1}},"children":[{"type":"paragraph","children":[{"type":"strong","position":{"start":{"line":13,"column":1},"end":{"line":13,"column":1}},"children":[{"type":"text","value":"Ingest & Curation","position":{"start":{"line":13,"column":1},"end":{"line":13,"column":1}},"key":"Eszg8SfL7e"}],"key":"Po3L8xMeal"},{"type":"text","value":": Data submitted to GDEX is reviewed, documented, and formatted to community standards","position":{"start":{"line":13,"column":1},"end":{"line":13,"column":1}},"key":"KxRf8jCMQV"}],"key":"tyjWohMLJ9"}],"key":"VrGJwEGPiX"},{"type":"listItem","spread":true,"position":{"start":{"line":14,"column":1},"end":{"line":14,"column":1}},"children":[{"type":"paragraph","children":[{"type":"strong","position":{"start":{"line":14,"column":1},"end":{"line":14,"column":1}},"children":[{"type":"text","value":"Discovery","position":{"start":{"line":14,"column":1},"end":{"line":14,"column":1}},"key":"Sr1JtDkn7r"}],"key":"ytletj24qv"},{"type":"text","value":": Rich metadata and search tools help users find the right dataset quickly","position":{"start":{"line":14,"column":1},"end":{"line":14,"column":1}},"key":"FveHV1ZwBE"}],"key":"lBrcqiFLeZ"}],"key":"lKBrk2grZO"},{"type":"listItem","spread":true,"position":{"start":{"line":15,"column":1},"end":{"line":15,"column":1}},"children":[{"type":"paragraph","children":[{"type":"strong","position":{"start":{"line":15,"column":1},"end":{"line":15,"column":1}},"children":[{"type":"text","value":"Access","position":{"start":{"line":15,"column":1},"end":{"line":15,"column":1}},"key":"AWZOLl9zVs"}],"key":"afdd7DCwHM"},{"type":"text","value":": Multiple access pathways — from bulk download to cloud streaming","position":{"start":{"line":15,"column":1},"end":{"line":15,"column":1}},"key":"JaWM6N2f19"}],"key":"BSAOG26h8A"}],"key":"a5xMGm6tsq"},{"type":"listItem","spread":true,"position":{"start":{"line":16,"column":1},"end":{"line":16,"column":1}},"children":[{"type":"paragraph","children":[{"type":"strong","position":{"start":{"line":16,"column":1},"end":{"line":16,"column":1}},"children":[{"type":"text","value":"Citation","position":{"start":{"line":16,"column":1},"end":{"line":16,"column":1}},"key":"FajgA8s3ci"}],"key":"UfxwbRr7oK"},{"type":"text","value":": Persistent identifiers (DOIs) ensure datasets are citable and contributions are credited","position":{"start":{"line":16,"column":1},"end":{"line":16,"column":1}},"key":"zPGma9z6lh"}],"key":"HJQpSls1uu"}],"key":"ZCuj6NoLhA"},{"type":"listItem","spread":true,"position":{"start":{"line":17,"column":1},"end":{"line":17,"column":1}},"children":[{"type":"paragraph","children":[{"type":"strong","position":{"start":{"line":17,"column":1},"end":{"line":17,"column":1}},"children":[{"type":"text","value":"Preservation","position":{"start":{"line":17,"column":1},"end":{"line":17,"column":1}},"key":"IQFxQJmSdY"}],"key":"vdbPV4zi8w"},{"type":"text","value":": GDEX provides long-term stewardship and data backups","position":{"start":{"line":17,"column":1},"end":{"line":17,"column":1}},"key":"KLv7IE07x3"}],"key":"xMJqf8h8S8"}],"key":"rXoOHr6nZj"},{"type":"listItem","spread":true,"position":{"start":{"line":18,"column":1},"end":{"line":18,"column":1}},"children":[{"type":"paragraph","children":[{"type":"strong","position":{"start":{"line":18,"column":1},"end":{"line":18,"column":1}},"children":[{"type":"text","value":"Stewardship","position":{"start":{"line":18,"column":1},"end":{"line":18,"column":1}},"key":"vkwIPQMy6A"}],"key":"R5veLFzuv5"},{"type":"text","value":": Science-educated staff assist users in solving problems and forwarding science.","position":{"start":{"line":18,"column":1},"end":{"line":18,"column":1}},"key":"xVXlbydc4k"}],"key":"zSW6L26bMR"}],"key":"dfyTe9bl1v"}],"key":"hEYYEe840u"}],"key":"mE5fjEGOWo"},{"type":"block","kind":"notebook-content","children":[{"type":"admonition","kind":"note","children":[{"type":"admonitionTitle","children":[{"type":"text","value":"Note","key":"sZdWet5D9x"}],"key":"iN21GsFLy4"},{"type":"paragraph","position":{"start":{"line":2,"column":1},"end":{"line":2,"column":1}},"children":[{"type":"text","value":"All GDEX datasets are freely accessible — no institutional login is required to browse, search, or download public datasets.","position":{"start":{"line":2,"column":1},"end":{"line":2,"column":1}},"key":"VXk7goRT9r"}],"key":"aQnbcP4BcE"}],"key":"chMZPtCWmC"}],"key":"vSIYlPNO2g"},{"type":"block","kind":"notebook-content","children":[{"type":"heading","depth":2,"position":{"start":{"line":1,"column":1},"end":{"line":1,"column":1}},"children":[{"type":"text","value":"Data Collections","position":{"start":{"line":1,"column":1},"end":{"line":1,"column":1}},"key":"WZeCEZD9Y4"}],"identifier":"data-collections","label":"Data Collections","html_id":"data-collections","implicit":true,"key":"g0rfeR6c0n"},{"type":"paragraph","position":{"start":{"line":3,"column":1},"end":{"line":3,"column":1}},"children":[{"type":"text","value":"GDEX hosts thousands of datasets spanning the full breadth of the geosciences. Collections range from petabytes of global reanalysis output to niche observational records from field campaigns.","position":{"start":{"line":3,"column":1},"end":{"line":3,"column":1}},"key":"dFommiFUaz"}],"key":"b9Rc1qtrhO"},{"type":"heading","depth":3,"position":{"start":{"line":5,"column":1},"end":{"line":5,"column":1}},"children":[{"type":"text","value":"Atmospheric and Climate Data","position":{"start":{"line":5,"column":1},"end":{"line":5,"column":1}},"key":"Pq1AkYOEN7"}],"identifier":"atmospheric-and-climate-data","label":"Atmospheric and Climate Data","html_id":"atmospheric-and-climate-data","implicit":true,"key":"XvUksnsw7f"},{"type":"table","position":{"start":{"line":7,"column":1},"end":{"line":12,"column":1}},"children":[{"type":"tableRow","position":{"start":{"line":7,"column":1},"end":{"line":7,"column":1}},"children":[{"type":"tableCell","header":true,"position":{"start":{"line":7,"column":1},"end":{"line":7,"column":1}},"children":[{"type":"text","value":"Category","position":{"start":{"line":7,"column":1},"end":{"line":7,"column":1}},"key":"LVg0AlsCK0"}],"key":"zP3NRN0PiZ"},{"type":"tableCell","header":true,"position":{"start":{"line":7,"column":1},"end":{"line":7,"column":1}},"children":[{"type":"text","value":"Example Datasets","position":{"start":{"line":7,"column":1},"end":{"line":7,"column":1}},"key":"RREfYpXqrs"}],"key":"IdfD8NOpMm"}],"key":"GgUCfTPqHt"},{"type":"tableRow","position":{"start":{"line":9,"column":1},"end":{"line":9,"column":1}},"children":[{"type":"tableCell","position":{"start":{"line":9,"column":1},"end":{"line":9,"column":1}},"children":[{"type":"text","value":"Global Reanalysis","position":{"start":{"line":9,"column":1},"end":{"line":9,"column":1}},"key":"gQkixV2p6j"}],"key":"Z9DG38iKkd"},{"type":"tableCell","position":{"start":{"line":9,"column":1},"end":{"line":9,"column":1}},"children":[{"type":"link","url":"https://gdex.ucar.edu/datasets/d633000/","position":{"start":{"line":9,"column":1},"end":{"line":9,"column":1}},"children":[{"type":"text","value":"ERA5","position":{"start":{"line":9,"column":1},"end":{"line":9,"column":1}},"key":"KwaCQ4RK2s"}],"urlSource":"https://gdex.ucar.edu/datasets/d633000/","key":"z7j0rSKOZu"},{"type":"text","value":", ","position":{"start":{"line":9,"column":1},"end":{"line":9,"column":1}},"key":"vk8Ome8hKq"},{"type":"link","url":"https://gdex.ucar.edu/datasets/d090002/","position":{"start":{"line":9,"column":1},"end":{"line":9,"column":1}},"children":[{"type":"text","value":"NCEP/NCAR Reanalysis","position":{"start":{"line":9,"column":1},"end":{"line":9,"column":1}},"key":"VcCHYBzV3t"}],"urlSource":"https://gdex.ucar.edu/datasets/d090002/","key":"jYHUpAS7vt"},{"type":"text","value":", ","position":{"start":{"line":9,"column":1},"end":{"line":9,"column":1}},"key":"FlL5ofogLs"},{"type":"link","url":"https://gdex.ucar.edu/datasets/d640000/","position":{"start":{"line":9,"column":1},"end":{"line":9,"column":1}},"children":[{"type":"text","value":"JRA-3Q","position":{"start":{"line":9,"column":1},"end":{"line":9,"column":1}},"key":"l34fA2i7gF"}],"urlSource":"https://gdex.ucar.edu/datasets/d640000/","key":"WSg59tlNoL"}],"key":"hoasX8ESsU"}],"key":"b9fakxSTbe"},{"type":"tableRow","position":{"start":{"line":10,"column":1},"end":{"line":10,"column":1}},"children":[{"type":"tableCell","position":{"start":{"line":10,"column":1},"end":{"line":10,"column":1}},"children":[{"type":"text","value":"Numerical Weather Prediction","position":{"start":{"line":10,"column":1},"end":{"line":10,"column":1}},"key":"YLGGRU78Vq"}],"key":"LjWmoQMmfv"},{"type":"tableCell","position":{"start":{"line":10,"column":1},"end":{"line":10,"column":1}},"children":[{"type":"link","url":"https://gdex.ucar.edu/datasets/d084001/","position":{"start":{"line":10,"column":1},"end":{"line":10,"column":1}},"children":[{"type":"text","value":"GFS","position":{"start":{"line":10,"column":1},"end":{"line":10,"column":1}},"key":"beoeqIbrql"}],"urlSource":"https://gdex.ucar.edu/datasets/d084001/","key":"JdZeNSGUJQ"},{"type":"text","value":", ECMWF forecasts","position":{"start":{"line":10,"column":1},"end":{"line":10,"column":1}},"key":"vvN7zMNcIe"}],"key":"kVUwTss9Ps"}],"key":"o7LsKNuGZk"},{"type":"tableRow","position":{"start":{"line":11,"column":1},"end":{"line":11,"column":1}},"children":[{"type":"tableCell","position":{"start":{"line":11,"column":1},"end":{"line":11,"column":1}},"children":[{"type":"text","value":"Climate Model Output","position":{"start":{"line":11,"column":1},"end":{"line":11,"column":1}},"key":"kztxJHj8V5"}],"key":"hJRkoy5wdv"},{"type":"tableCell","position":{"start":{"line":11,"column":1},"end":{"line":11,"column":1}},"children":[{"type":"link","url":"https://gdex.ucar.edu/gsearch/dataset-search/?q=cesm2","position":{"start":{"line":11,"column":1},"end":{"line":11,"column":1}},"children":[{"type":"text","value":"CESM Large Ensemble","position":{"start":{"line":11,"column":1},"end":{"line":11,"column":1}},"key":"I5qhJhGhaw"}],"urlSource":"https://gdex.ucar.edu/gsearch/dataset-search/?q=cesm2","key":"gHwgwMDaKX"},{"type":"text","value":", CMIP-era simulations","position":{"start":{"line":11,"column":1},"end":{"line":11,"column":1}},"key":"agy7FipuNI"}],"key":"oIth35ubm0"}],"key":"gHNU77NyfH"},{"type":"tableRow","position":{"start":{"line":12,"column":1},"end":{"line":12,"column":1}},"children":[{"type":"tableCell","position":{"start":{"line":12,"column":1},"end":{"line":12,"column":1}},"children":[{"type":"text","value":"Observational Records","position":{"start":{"line":12,"column":1},"end":{"line":12,"column":1}},"key":"Kg1PSt4c3R"}],"key":"z0JvVacYmq"},{"type":"tableCell","position":{"start":{"line":12,"column":1},"end":{"line":12,"column":1}},"children":[{"type":"text","value":"Radiosondes, surface stations, rawinsondes","position":{"start":{"line":12,"column":1},"end":{"line":12,"column":1}},"key":"v9F9T2LN3T"}],"key":"C5XBjnW19g"}],"key":"IPlCOYXROq"}],"key":"Pjb2nmzgHm"},{"type":"heading","depth":3,"position":{"start":{"line":14,"column":1},"end":{"line":14,"column":1}},"children":[{"type":"text","value":"Ocean and Earth System Data","position":{"start":{"line":14,"column":1},"end":{"line":14,"column":1}},"key":"DFyhHp5kcS"}],"identifier":"ocean-and-earth-system-data","label":"Ocean and Earth System Data","html_id":"ocean-and-earth-system-data","implicit":true,"key":"RP4q9UsYeO"},{"type":"list","ordered":false,"spread":false,"position":{"start":{"line":16,"column":1},"end":{"line":19,"column":1}},"children":[{"type":"listItem","spread":true,"position":{"start":{"line":16,"column":1},"end":{"line":16,"column":1}},"children":[{"type":"paragraph","children":[{"type":"strong","position":{"start":{"line":16,"column":1},"end":{"line":16,"column":1}},"children":[{"type":"text","value":"Oceanographic","position":{"start":{"line":16,"column":1},"end":{"line":16,"column":1}},"key":"wBKm66KS8q"}],"key":"xhqL98BtTO"},{"type":"text","value":": ","position":{"start":{"line":16,"column":1},"end":{"line":16,"column":1}},"key":"mU3VoK7Zpj"},{"type":"link","url":"https://gdex.ucar.edu/datasets/d548000/","position":{"start":{"line":16,"column":1},"end":{"line":16,"column":1}},"children":[{"type":"text","value":"ICOADS","position":{"start":{"line":16,"column":1},"end":{"line":16,"column":1}},"key":"NzYeP4bJsL"}],"urlSource":"https://gdex.ucar.edu/datasets/d548000/","key":"OhjauBHbKi"},{"type":"text","value":" — the International Comprehensive Ocean-Atmosphere Data Set, spanning centuries of marine surface observations","position":{"start":{"line":16,"column":1},"end":{"line":16,"column":1}},"key":"ArdWV6hfDi"}],"key":"oJUzL6qTcS"}],"key":"AoTgY8ivni"},{"type":"listItem","spread":true,"position":{"start":{"line":17,"column":1},"end":{"line":17,"column":1}},"children":[{"type":"paragraph","children":[{"type":"strong","position":{"start":{"line":17,"column":1},"end":{"line":17,"column":1}},"children":[{"type":"text","value":"Land surface","position":{"start":{"line":17,"column":1},"end":{"line":17,"column":1}},"key":"tat6ahmlgE"}],"key":"qNDx1EeOyt"},{"type":"text","value":": Soil moisture, vegetation, and land-use datasets supporting land-atmosphere interaction research","position":{"start":{"line":17,"column":1},"end":{"line":17,"column":1}},"key":"GnDIorX1yO"}],"key":"H9Jg9UQHXd"}],"key":"EXiRzea35i"},{"type":"listItem","spread":true,"position":{"start":{"line":18,"column":1},"end":{"line":19,"column":1}},"children":[{"type":"paragraph","children":[{"type":"strong","position":{"start":{"line":18,"column":1},"end":{"line":18,"column":1}},"children":[{"type":"text","value":"Cryosphere","position":{"start":{"line":18,"column":1},"end":{"line":18,"column":1}},"key":"Xi84YUchCf"}],"key":"Ny1VelFxfU"},{"type":"text","value":": Sea ice concentration, snow cover, and ice sheet data","position":{"start":{"line":18,"column":1},"end":{"line":18,"column":1}},"key":"aL8LhhezDj"}],"key":"w33sFXUqZG"}],"key":"DNOBrzQKD9"}],"key":"B1dP4tgFjt"},{"type":"heading","depth":3,"position":{"start":{"line":20,"column":1},"end":{"line":20,"column":1}},"children":[{"type":"text","value":"File Formats","position":{"start":{"line":20,"column":1},"end":{"line":20,"column":1}},"key":"kGqCYm3uCj"}],"identifier":"file-formats","label":"File Formats","html_id":"file-formats","implicit":true,"key":"dYg5it1Baz"},{"type":"paragraph","position":{"start":{"line":22,"column":1},"end":{"line":22,"column":1}},"children":[{"type":"text","value":"GDEX datasets are available in community-standard formats, increasingly including cloud-optimized options:","position":{"start":{"line":22,"column":1},"end":{"line":22,"column":1}},"key":"a0D7fLivLI"}],"key":"dysFnTBrc2"},{"type":"table","position":{"start":{"line":24,"column":1},"end":{"line":31,"column":1}},"children":[{"type":"tableRow","position":{"start":{"line":24,"column":1},"end":{"line":24,"column":1}},"children":[{"type":"tableCell","header":true,"position":{"start":{"line":24,"column":1},"end":{"line":24,"column":1}},"children":[{"type":"text","value":"Format","position":{"start":{"line":24,"column":1},"end":{"line":24,"column":1}},"key":"JsFOGyB5sv"}],"key":"TgZ6M95WBd"},{"type":"tableCell","header":true,"position":{"start":{"line":24,"column":1},"end":{"line":24,"column":1}},"children":[{"type":"text","value":"Use Case","position":{"start":{"line":24,"column":1},"end":{"line":24,"column":1}},"key":"SLkXqODLkU"}],"key":"QF14Ve7MoR"}],"key":"EDAAeF9czL"},{"type":"tableRow","position":{"start":{"line":26,"column":1},"end":{"line":26,"column":1}},"children":[{"type":"tableCell","position":{"start":{"line":26,"column":1},"end":{"line":26,"column":1}},"children":[{"type":"link","url":"https://docs.unidata.ucar.edu/netcdf-c/current/faq.html","position":{"start":{"line":26,"column":1},"end":{"line":26,"column":1}},"children":[{"type":"text","value":"NetCDF4","position":{"start":{"line":26,"column":1},"end":{"line":26,"column":1}},"key":"UTgOVWUjkV"}],"urlSource":"https://docs.unidata.ucar.edu/netcdf-c/current/faq.html","key":"FD83XX3uaJ"}],"key":"JmAisk6n8W"},{"type":"tableCell","position":{"start":{"line":26,"column":1},"end":{"line":26,"column":1}},"children":[{"type":"text","value":"Standard for gridded geoscience data","position":{"start":{"line":26,"column":1},"end":{"line":26,"column":1}},"key":"qA0veR39yd"}],"key":"xWrMRxQ727"}],"key":"alSjvYxvmj"},{"type":"tableRow","position":{"start":{"line":27,"column":1},"end":{"line":27,"column":1}},"children":[{"type":"tableCell","position":{"start":{"line":27,"column":1},"end":{"line":27,"column":1}},"children":[{"type":"link","url":"https://codes.ecmwf.int/grib/format/grib2/overview/","position":{"start":{"line":27,"column":1},"end":{"line":27,"column":1}},"children":[{"type":"text","value":"Grib2","position":{"start":{"line":27,"column":1},"end":{"line":27,"column":1}},"key":"pDINWwXvkv"}],"urlSource":"https://codes.ecmwf.int/grib/format/grib2/overview/","key":"aHAseW6oSp"}],"key":"X7bPBYifLz"},{"type":"tableCell","position":{"start":{"line":27,"column":1},"end":{"line":27,"column":1}},"children":[{"type":"text","value":"NWP model output from operational centers","position":{"start":{"line":27,"column":1},"end":{"line":27,"column":1}},"key":"hz0sreVjdu"}],"key":"yA8bwTug4n"}],"key":"N3JjCYllbn"},{"type":"tableRow","position":{"start":{"line":28,"column":1},"end":{"line":28,"column":1}},"children":[{"type":"tableCell","position":{"start":{"line":28,"column":1},"end":{"line":28,"column":1}},"children":[{"type":"link","url":"https://zarr.dev/","position":{"start":{"line":28,"column":1},"end":{"line":28,"column":1}},"children":[{"type":"text","value":"Zarr","position":{"start":{"line":28,"column":1},"end":{"line":28,"column":1}},"key":"hXsWrVH2dc"}],"urlSource":"https://zarr.dev/","key":"vOmCMUyjlD"}],"key":"n6bMTgPAhB"},{"type":"tableCell","position":{"start":{"line":28,"column":1},"end":{"line":28,"column":1}},"children":[{"type":"text","value":"Cloud-native, chunked array storage","position":{"start":{"line":28,"column":1},"end":{"line":28,"column":1}},"key":"aJtzPmsD4a"}],"key":"qWrCStrVPf"}],"key":"okdKNDeWcJ"},{"type":"tableRow","position":{"start":{"line":29,"column":1},"end":{"line":29,"column":1}},"children":[{"type":"tableCell","position":{"start":{"line":29,"column":1},"end":{"line":29,"column":1}},"children":[{"type":"link","url":"https://fsspec.github.io/kerchunk/","position":{"start":{"line":29,"column":1},"end":{"line":29,"column":1}},"children":[{"type":"text","value":"Kerchunk","position":{"start":{"line":29,"column":1},"end":{"line":29,"column":1}},"key":"vnSQCWJmiM"}],"urlSource":"https://fsspec.github.io/kerchunk/","key":"fIR8x1i5qN"}],"key":"Efrhi8uwoa"},{"type":"tableCell","position":{"start":{"line":29,"column":1},"end":{"line":29,"column":1}},"children":[{"type":"text","value":"Virtual consolidated metadata for remote access","position":{"start":{"line":29,"column":1},"end":{"line":29,"column":1}},"key":"swacURz56M"}],"key":"zO9y9o0fr5"}],"key":"HPmF8XpKAx"},{"type":"tableRow","position":{"start":{"line":30,"column":1},"end":{"line":30,"column":1}},"children":[{"type":"tableCell","position":{"start":{"line":30,"column":1},"end":{"line":30,"column":1}},"children":[{"type":"link","url":"https://www.ecmwf.int/sites/default/files/elibrary/2008/80533-bufr-users-guide_0.pdf","position":{"start":{"line":30,"column":1},"end":{"line":30,"column":1}},"children":[{"type":"text","value":"BUFR","position":{"start":{"line":30,"column":1},"end":{"line":30,"column":1}},"key":"iM9yA3ouTJ"}],"urlSource":"https://www.ecmwf.int/sites/default/files/elibrary/2008/80533-bufr-users-guide_0.pdf","key":"Y008Wh05dh"}],"key":"kdjXsqY8MH"},{"type":"tableCell","position":{"start":{"line":30,"column":1},"end":{"line":30,"column":1}},"children":[{"type":"text","value":"Encoded observational data","position":{"start":{"line":30,"column":1},"end":{"line":30,"column":1}},"key":"we8husYpda"}],"key":"Pptsqv1CLm"}],"key":"c16uel9zEF"},{"type":"tableRow","position":{"start":{"line":31,"column":1},"end":{"line":31,"column":1}},"children":[{"type":"tableCell","position":{"start":{"line":31,"column":1},"end":{"line":31,"column":1}},"children":[{"type":"text","value":"Proprietary binary","position":{"start":{"line":31,"column":1},"end":{"line":31,"column":1}},"key":"Kr2snalzDk"}],"key":"MaiSh5njRD"},{"type":"tableCell","position":{"start":{"line":31,"column":1},"end":{"line":31,"column":1}},"children":[{"type":"text","value":"Legacy datasets in original format","position":{"start":{"line":31,"column":1},"end":{"line":31,"column":1}},"key":"HhxzuN5a2M"}],"key":"O7V3vd3xh4"}],"key":"CpPO25uDyY"}],"key":"YOOQSEMGVh"}],"key":"tkpc0kF3Ml"},{"type":"block","kind":"notebook-content","children":[{"type":"heading","depth":2,"position":{"start":{"line":1,"column":1},"end":{"line":1,"column":1}},"children":[{"type":"text","value":"Services and Tools","position":{"start":{"line":1,"column":1},"end":{"line":1,"column":1}},"key":"DwUoGrLbHM"}],"identifier":"services-and-tools","label":"Services and Tools","html_id":"services-and-tools","implicit":true,"key":"HxQITptd4D"},{"type":"paragraph","position":{"start":{"line":3,"column":1},"end":{"line":4,"column":1}},"children":[{"type":"text","value":"GDEX offers a comprehensive suite of services to help researchers at every stage of their workflow.\nThese include,","position":{"start":{"line":3,"column":1},"end":{"line":3,"column":1}},"key":"LlFkwYTC5q"}],"key":"NAxZKq3BUo"},{"type":"table","position":{"start":{"line":6,"column":1},"end":{"line":13,"column":1}},"children":[{"type":"tableRow","position":{"start":{"line":6,"column":1},"end":{"line":6,"column":1}},"children":[{"type":"tableCell","header":true,"position":{"start":{"line":6,"column":1},"end":{"line":6,"column":1}},"children":[{"type":"text","value":"Service","position":{"start":{"line":6,"column":1},"end":{"line":6,"column":1}},"key":"sXG3C9bxKK"}],"key":"ESnxdhIoic"},{"type":"tableCell","header":true,"position":{"start":{"line":6,"column":1},"end":{"line":6,"column":1}},"children":[{"type":"text","value":"Use","position":{"start":{"line":6,"column":1},"end":{"line":6,"column":1}},"key":"M1RyABQm37"}],"key":"IfRYt7bg9y"}],"key":"gUjBf86VWb"},{"type":"tableRow","position":{"start":{"line":8,"column":1},"end":{"line":8,"column":1}},"children":[{"type":"tableCell","position":{"start":{"line":8,"column":1},"end":{"line":8,"column":1}},"children":[{"type":"strong","position":{"start":{"line":8,"column":1},"end":{"line":8,"column":1}},"children":[{"type":"text","value":"Discovery and Search","position":{"start":{"line":8,"column":1},"end":{"line":8,"column":1}},"key":"Q1zTK2XZCe"}],"key":"FEvcblNy3n"}],"key":"WjHbV1QhLE"},{"type":"tableCell","position":{"start":{"line":8,"column":1},"end":{"line":8,"column":1}},"children":[{"type":"text","value":"Dataset and file-level search","position":{"start":{"line":8,"column":1},"end":{"line":8,"column":1}},"key":"eSiCVCrtGX"}],"key":"xMuWdsqh95"}],"key":"Ekkg3QvZpS"},{"type":"tableRow","position":{"start":{"line":9,"column":1},"end":{"line":9,"column":1}},"children":[{"type":"tableCell","position":{"start":{"line":9,"column":1},"end":{"line":9,"column":1}},"children":[{"type":"strong","position":{"start":{"line":9,"column":1},"end":{"line":9,"column":1}},"children":[{"type":"text","value":"Data Access Pathways","position":{"start":{"line":9,"column":1},"end":{"line":9,"column":1}},"key":"fi8sXoKUe2"}],"key":"t59U8gTzmf"}],"key":"N8qifNWD5c"},{"type":"tableCell","position":{"start":{"line":9,"column":1},"end":{"line":9,"column":1}},"children":[{"type":"text","value":"Variety of data access methods for every situation","position":{"start":{"line":9,"column":1},"end":{"line":9,"column":1}},"key":"n2xw6fChio"}],"key":"AsjeL4zbUW"}],"key":"MHvzuBxotM"},{"type":"tableRow","position":{"start":{"line":10,"column":1},"end":{"line":10,"column":1}},"children":[{"type":"tableCell","position":{"start":{"line":10,"column":1},"end":{"line":10,"column":1}},"children":[{"type":"strong","position":{"start":{"line":10,"column":1},"end":{"line":10,"column":1}},"children":[{"type":"text","value":"Subsetting","position":{"start":{"line":10,"column":1},"end":{"line":10,"column":1}},"key":"aX1HVusZyF"}],"key":"BEcmJEcxgY"}],"key":"Yy6zIbptAe"},{"type":"tableCell","position":{"start":{"line":10,"column":1},"end":{"line":10,"column":1}},"children":[{"type":"text","value":"HPC powered subsetting to only get the data you need","position":{"start":{"line":10,"column":1},"end":{"line":10,"column":1}},"key":"dFKuo1UodN"}],"key":"fXjBsEece4"}],"key":"wXAWJLn0kX"},{"type":"tableRow","position":{"start":{"line":11,"column":1},"end":{"line":11,"column":1}},"children":[{"type":"tableCell","position":{"start":{"line":11,"column":1},"end":{"line":11,"column":1}},"children":[{"type":"strong","position":{"start":{"line":11,"column":1},"end":{"line":11,"column":1}},"children":[{"type":"text","value":"Compute Proximate Access","position":{"start":{"line":11,"column":1},"end":{"line":11,"column":1}},"key":"bDCXrNkWBe"}],"key":"erE3fppE80"}],"key":"mFdYxncn7Z"},{"type":"tableCell","position":{"start":{"line":11,"column":1},"end":{"line":11,"column":1}},"children":[{"type":"text","value":"Direct data access supported by NSF NCAR HPC resources","position":{"start":{"line":11,"column":1},"end":{"line":11,"column":1}},"key":"E1gv4ZeDk7"}],"key":"YJY2iml8DR"}],"key":"mvjfQgHx3p"},{"type":"tableRow","position":{"start":{"line":12,"column":1},"end":{"line":12,"column":1}},"children":[{"type":"tableCell","position":{"start":{"line":12,"column":1},"end":{"line":12,"column":1}},"children":[{"type":"strong","position":{"start":{"line":12,"column":1},"end":{"line":12,"column":1}},"children":[{"type":"text","value":"API","position":{"start":{"line":12,"column":1},"end":{"line":12,"column":1}},"key":"WOzgwImmVx"}],"key":"Aob9UMHMIl"}],"key":"QbMxyzSq94"},{"type":"tableCell","position":{"start":{"line":12,"column":1},"end":{"line":12,"column":1}},"children":[{"type":"text","value":"Integration directly into data science workflows","position":{"start":{"line":12,"column":1},"end":{"line":12,"column":1}},"key":"AdFm2glK7M"}],"key":"Mbm4l2onyA"}],"key":"Ej3jZJkBqt"},{"type":"tableRow","position":{"start":{"line":13,"column":1},"end":{"line":13,"column":1}},"children":[{"type":"tableCell","position":{"start":{"line":13,"column":1},"end":{"line":13,"column":1}},"children":[{"type":"strong","position":{"start":{"line":13,"column":1},"end":{"line":13,"column":1}},"children":[{"type":"text","value":"Dataset Citation","position":{"start":{"line":13,"column":1},"end":{"line":13,"column":1}},"key":"Ja29v4VoU3"}],"key":"AxUEA1wU3H"}],"key":"umvaV6kYVc"},{"type":"tableCell","position":{"start":{"line":13,"column":1},"end":{"line":13,"column":1}},"children":[{"type":"text","value":"Rich metadata supporting DOI and citation tools","position":{"start":{"line":13,"column":1},"end":{"line":13,"column":1}},"key":"VgTbFWaadc"}],"key":"b8AaGdO5AO"}],"key":"QLzsRj6gKt"}],"key":"pzj0HSLaWH"}],"key":"POgt3y1xDE"},{"type":"block","kind":"notebook-content","children":[{"type":"admonition","kind":"seealso","children":[{"type":"admonitionTitle","children":[{"type":"text","value":"See Also","key":"wSgAvS9dV4"}],"key":"Jgmylqgjkb"},{"type":"paragraph","position":{"start":{"line":2,"column":1},"end":{"line":2,"column":1}},"children":[{"type":"text","value":"The ","position":{"start":{"line":2,"column":1},"end":{"line":2,"column":1}},"key":"Gm7ZWT5QUt"},{"type":"strong","position":{"start":{"line":2,"column":1},"end":{"line":2,"column":1}},"children":[{"type":"text","value":"Services","position":{"start":{"line":2,"column":1},"end":{"line":2,"column":1}},"key":"lbV2JvuLCs"}],"key":"JwVKK69vMT"},{"type":"text","value":" section of this cookbook has dedicated notebooks for each access pathway: TDS/OPeNDAP, Zarr streaming, the REST API, direct download, and Globus transfer.","position":{"start":{"line":2,"column":1},"end":{"line":2,"column":1}},"key":"c2mre2v3Ah"}],"key":"qXY94hgfHq"}],"key":"FF2rPeGJlI"}],"key":"TvvLOfl5CG"},{"type":"block","kind":"notebook-content","children":[{"type":"heading","depth":2,"position":{"start":{"line":1,"column":1},"end":{"line":1,"column":1}},"children":[{"type":"text","value":"Data Submission","position":{"start":{"line":1,"column":1},"end":{"line":1,"column":1}},"key":"yNRvoooVRt"}],"identifier":"data-submission","label":"Data Submission","html_id":"data-submission","implicit":true,"key":"kkgYUnm7UM"},{"type":"paragraph","position":{"start":{"line":3,"column":1},"end":{"line":3,"column":1}},"children":[{"type":"text","value":"GDEX accepts data submissions from the broader scientific community. Archiving your data with GDEX is a way to ensure it reaches the widest possible audience and remains accessible for the long term.","position":{"start":{"line":3,"column":1},"end":{"line":3,"column":1}},"key":"osTIPNJrS5"}],"key":"AaV13JFHtx"}],"key":"WV12rCiXHN"},{"type":"block","kind":"notebook-content","children":[{"type":"image","url":"/gdex-cookbook/build/submit-data-5df81821ed4cf9bd44c43d7389bba6a8.png","alt":"Submit Data View","width":"90%","align":"center","key":"ImOy8CuhNn","urlSource":"../../images/submit-data.png"}],"key":"fmQoaHjKv4"},{"type":"block","kind":"notebook-content","children":[{"type":"heading","depth":3,"position":{"start":{"line":4,"column":1},"end":{"line":4,"column":1}},"children":[{"type":"text","value":"Who Can Submit?","position":{"start":{"line":4,"column":1},"end":{"line":4,"column":1}},"key":"KdJwE54D75"}],"identifier":"who-can-submit","label":"Who Can Submit?","html_id":"who-can-submit","implicit":true,"key":"BNcJV0K24o"},{"type":"paragraph","position":{"start":{"line":6,"column":1},"end":{"line":6,"column":1}},"children":[{"type":"text","value":"Data submission is open to:","position":{"start":{"line":6,"column":1},"end":{"line":6,"column":1}},"key":"C0mJhpI1il"}],"key":"FgfVS9dFrd"},{"type":"list","ordered":false,"spread":false,"position":{"start":{"line":8,"column":1},"end":{"line":11,"column":1}},"children":[{"type":"listItem","spread":true,"position":{"start":{"line":8,"column":1},"end":{"line":8,"column":1}},"children":[{"type":"paragraph","children":[{"type":"strong","position":{"start":{"line":8,"column":1},"end":{"line":8,"column":1}},"children":[{"type":"text","value":"NSF NCAR scientists and collaborators","position":{"start":{"line":8,"column":1},"end":{"line":8,"column":1}},"key":"gJ9DKXne5S"}],"key":"rXbAADShPO"},{"type":"text","value":" conducting funded research","position":{"start":{"line":8,"column":1},"end":{"line":8,"column":1}},"key":"OUGy06pYkM"}],"key":"f1CzpNA6Xt"}],"key":"bSsHhYQ1Kk"},{"type":"listItem","spread":true,"position":{"start":{"line":9,"column":1},"end":{"line":9,"column":1}},"children":[{"type":"paragraph","children":[{"type":"strong","position":{"start":{"line":9,"column":1},"end":{"line":9,"column":1}},"children":[{"type":"text","value":"University researchers","position":{"start":{"line":9,"column":1},"end":{"line":9,"column":1}},"key":"uEwnSvysgG"}],"key":"PKqOFycWVN"},{"type":"text","value":" and UCAR member institutions","position":{"start":{"line":9,"column":1},"end":{"line":9,"column":1}},"key":"E9HEQaVZ9Z"}],"key":"gysutGKCmf"}],"key":"vHIC0AYY4l"},{"type":"listItem","spread":true,"position":{"start":{"line":10,"column":1},"end":{"line":11,"column":1}},"children":[{"type":"paragraph","children":[{"type":"strong","position":{"start":{"line":10,"column":1},"end":{"line":10,"column":1}},"children":[{"type":"text","value":"Project teams","position":{"start":{"line":10,"column":1},"end":{"line":10,"column":1}},"key":"BSa3ZMzGQi"}],"key":"J9XZpjO33r"},{"type":"text","value":" with NSF or other federally funded grants that require a data management plan","position":{"start":{"line":10,"column":1},"end":{"line":10,"column":1}},"key":"Am8MbxFI7P"}],"key":"VjKv0ABdCN"}],"key":"M496qBN6dP"}],"key":"rt8ZLeJAlH"},{"type":"paragraph","position":{"start":{"line":12,"column":1},"end":{"line":12,"column":1}},"children":[{"type":"text","value":"If you are unsure whether your dataset is a good fit, contact the GDEX team at ","position":{"start":{"line":12,"column":1},"end":{"line":12,"column":1}},"key":"UZmAwKdIbb"},{"type":"link","url":"mailto:datahelp@ucar.edu","position":{"start":{"line":12,"column":1},"end":{"line":12,"column":1}},"children":[{"type":"text","value":"datahelp@ucar.edu","position":{"start":{"line":12,"column":1},"end":{"line":12,"column":1}},"key":"CFP6Lpevbk"}],"urlSource":"mailto:datahelp@ucar.edu","key":"bFCKTp7yG5"},{"type":"text","value":".","position":{"start":{"line":12,"column":1},"end":{"line":12,"column":1}},"key":"oBYhyHJr3Z"}],"key":"NrJPcItdZQ"},{"type":"heading","depth":3,"position":{"start":{"line":14,"column":1},"end":{"line":14,"column":1}},"children":[{"type":"text","value":"What Types of Data Are Accepted?","position":{"start":{"line":14,"column":1},"end":{"line":14,"column":1}},"key":"A49KSygbkT"}],"identifier":"what-types-of-data-are-accepted","label":"What Types of Data Are Accepted?","html_id":"what-types-of-data-are-accepted","implicit":true,"key":"WUUV5yjyg7"},{"type":"paragraph","position":{"start":{"line":16,"column":1},"end":{"line":16,"column":1}},"children":[{"type":"text","value":"GDEX prioritizes datasets that:","position":{"start":{"line":16,"column":1},"end":{"line":16,"column":1}},"key":"iNBe2iP3W7"}],"key":"PXWt87kY1z"},{"type":"list","ordered":false,"spread":false,"position":{"start":{"line":18,"column":1},"end":{"line":22,"column":1}},"children":[{"type":"listItem","spread":true,"position":{"start":{"line":18,"column":1},"end":{"line":18,"column":1}},"children":[{"type":"paragraph","children":[{"type":"text","value":"Are of ","position":{"start":{"line":18,"column":1},"end":{"line":18,"column":1}},"key":"WvPDsyIWkF"},{"type":"strong","position":{"start":{"line":18,"column":1},"end":{"line":18,"column":1}},"children":[{"type":"text","value":"broad community interest","position":{"start":{"line":18,"column":1},"end":{"line":18,"column":1}},"key":"E4AfKUfeWC"}],"key":"XtcoeN36o9"},{"type":"text","value":" for atmospheric, oceanic, or related geoscience research","position":{"start":{"line":18,"column":1},"end":{"line":18,"column":1}},"key":"R3TlYwaGQi"}],"key":"oKEjOUumjE"}],"key":"HtydrB5oEr"},{"type":"listItem","spread":true,"position":{"start":{"line":19,"column":1},"end":{"line":19,"column":1}},"children":[{"type":"paragraph","children":[{"type":"text","value":"Come with sufficient ","position":{"start":{"line":19,"column":1},"end":{"line":19,"column":1}},"key":"y1CrSJIqIN"},{"type":"strong","position":{"start":{"line":19,"column":1},"end":{"line":19,"column":1}},"children":[{"type":"text","value":"documentation and metadata","position":{"start":{"line":19,"column":1},"end":{"line":19,"column":1}},"key":"tqnD859Ack"}],"key":"HpZxS6Bk9T"},{"type":"text","value":" to make the data reusable","position":{"start":{"line":19,"column":1},"end":{"line":19,"column":1}},"key":"reYnXRQTR8"}],"key":"Yw9zgZVNi3"}],"key":"xrHpNqdYWa"},{"type":"listItem","spread":true,"position":{"start":{"line":20,"column":1},"end":{"line":20,"column":1}},"children":[{"type":"paragraph","children":[{"type":"text","value":"Are in ","position":{"start":{"line":20,"column":1},"end":{"line":20,"column":1}},"key":"TMfczuR6fL"},{"type":"strong","position":{"start":{"line":20,"column":1},"end":{"line":20,"column":1}},"children":[{"type":"text","value":"community-standard formats","position":{"start":{"line":20,"column":1},"end":{"line":20,"column":1}},"key":"Hn2PJJ51WG"}],"key":"HzzNEDNO9q"},{"type":"text","value":" (or can be converted to them)","position":{"start":{"line":20,"column":1},"end":{"line":20,"column":1}},"key":"V84ytZe7tW"}],"key":"OtfW2twtlb"}],"key":"HBImuEsD57"},{"type":"listItem","spread":true,"position":{"start":{"line":21,"column":1},"end":{"line":22,"column":1}},"children":[{"type":"paragraph","children":[{"type":"text","value":"Represent ","position":{"start":{"line":21,"column":1},"end":{"line":21,"column":1}},"key":"b63v5yTFar"},{"type":"strong","position":{"start":{"line":21,"column":1},"end":{"line":21,"column":1}},"children":[{"type":"text","value":"unique or irreplaceable","position":{"start":{"line":21,"column":1},"end":{"line":21,"column":1}},"key":"mQFQIS9qoZ"}],"key":"qCQBX98dBv"},{"type":"text","value":" observational records or model output","position":{"start":{"line":21,"column":1},"end":{"line":21,"column":1}},"key":"WvvSXuhSbG"}],"key":"S8fl05svqU"}],"key":"EweHb8A8yU"}],"key":"Y0YfDjvqzd"},{"type":"heading","depth":3,"position":{"start":{"line":23,"column":1},"end":{"line":23,"column":1}},"children":[{"type":"text","value":"The Submission Process","position":{"start":{"line":23,"column":1},"end":{"line":23,"column":1}},"key":"mlRkUP7xHQ"}],"identifier":"the-submission-process","label":"The Submission Process","html_id":"the-submission-process","implicit":true,"key":"x4vZx450TZ"},{"type":"list","ordered":true,"start":1,"spread":false,"position":{"start":{"line":25,"column":1},"end":{"line":30,"column":1}},"children":[{"type":"listItem","spread":true,"position":{"start":{"line":25,"column":1},"end":{"line":25,"column":1}},"children":[{"type":"paragraph","children":[{"type":"strong","position":{"start":{"line":25,"column":1},"end":{"line":25,"column":1}},"children":[{"type":"text","value":"Contact the GDEX team","position":{"start":{"line":25,"column":1},"end":{"line":25,"column":1}},"key":"skedsMzPWW"}],"key":"hlCpQIzuRW"},{"type":"text","value":" — ","position":{"start":{"line":25,"column":1},"end":{"line":25,"column":1}},"key":"GMfL4Hz82Y"},{"type":"link","url":"https://gdex.ucar.edu/resources/submit-data/","position":{"start":{"line":25,"column":1},"end":{"line":25,"column":1}},"children":[{"type":"text","value":"Submit","position":{"start":{"line":25,"column":1},"end":{"line":25,"column":1}},"key":"J097mAGZiG"}],"urlSource":"https://gdex.ucar.edu/resources/submit-data/","key":"nXeyWiX9hI"},{"type":"text","value":" your data and discuss its suitability with the GDEX team","position":{"start":{"line":25,"column":1},"end":{"line":25,"column":1}},"key":"kOgVSfOXJz"}],"key":"WPPKtC6YVF"}],"key":"hMGy4PhSMT"},{"type":"listItem","spread":true,"position":{"start":{"line":26,"column":1},"end":{"line":26,"column":1}},"children":[{"type":"paragraph","children":[{"type":"strong","position":{"start":{"line":26,"column":1},"end":{"line":26,"column":1}},"children":[{"type":"text","value":"Prepare your data","position":{"start":{"line":26,"column":1},"end":{"line":26,"column":1}},"key":"Gxls3tCSOj"}],"key":"wjnpIlBYzV"},{"type":"text","value":" — Work with the GDEX team to ensure your data and metadata meet community standards","position":{"start":{"line":26,"column":1},"end":{"line":26,"column":1}},"key":"WPCJNq4Yd0"}],"key":"Xm0SasdGYy"}],"key":"qLesYH1k2e"},{"type":"listItem","spread":true,"position":{"start":{"line":27,"column":1},"end":{"line":27,"column":1}},"children":[{"type":"paragraph","children":[{"type":"strong","position":{"start":{"line":27,"column":1},"end":{"line":27,"column":1}},"children":[{"type":"text","value":"Transfer your data","position":{"start":{"line":27,"column":1},"end":{"line":27,"column":1}},"key":"N8tGKzCZrR"}],"key":"RBsOez8CO8"},{"type":"text","value":" — GDEX supports transfer via Globus, HTTPS, or other methods depending on data volume","position":{"start":{"line":27,"column":1},"end":{"line":27,"column":1}},"key":"Z4PbV1IIHz"}],"key":"HafgjdiyIa"}],"key":"KwCjy84WHT"},{"type":"listItem","spread":true,"position":{"start":{"line":28,"column":1},"end":{"line":28,"column":1}},"children":[{"type":"paragraph","children":[{"type":"strong","position":{"start":{"line":28,"column":1},"end":{"line":28,"column":1}},"children":[{"type":"text","value":"Curation and review","position":{"start":{"line":28,"column":1},"end":{"line":28,"column":1}},"key":"QdabPIZWA6"}],"key":"dCZvMI3PAQ"},{"type":"text","value":" — The GDEX team reviews, documents, and organizes your dataset","position":{"start":{"line":28,"column":1},"end":{"line":28,"column":1}},"key":"PzRyfQXMHK"}],"key":"lthTv1g2u0"}],"key":"bN5Ucy7iBC"},{"type":"listItem","spread":true,"position":{"start":{"line":29,"column":1},"end":{"line":30,"column":1}},"children":[{"type":"paragraph","children":[{"type":"strong","position":{"start":{"line":29,"column":1},"end":{"line":29,"column":1}},"children":[{"type":"text","value":"Publication and DOI","position":{"start":{"line":29,"column":1},"end":{"line":29,"column":1}},"key":"u43GDnys0B"}],"key":"gVzH0WGMMq"},{"type":"text","value":" — Your dataset is published with a persistent DOI, making it citable in publications","position":{"start":{"line":29,"column":1},"end":{"line":29,"column":1}},"key":"ss5RC1ewOP"}],"key":"w4Wbc4qDss"}],"key":"cQO8SBt0A4"}],"key":"Q9EtQCzNsu"},{"type":"heading","depth":3,"position":{"start":{"line":31,"column":1},"end":{"line":31,"column":1}},"children":[{"type":"text","value":"Benefits of Archiving with GDEX","position":{"start":{"line":31,"column":1},"end":{"line":31,"column":1}},"key":"PVLzK9RvZY"}],"identifier":"benefits-of-archiving-with-gdex","label":"Benefits of Archiving with GDEX","html_id":"benefits-of-archiving-with-gdex","implicit":true,"key":"ZgwAE6JewG"},{"type":"list","ordered":false,"spread":false,"position":{"start":{"line":33,"column":1},"end":{"line":38,"column":1}},"children":[{"type":"listItem","spread":true,"position":{"start":{"line":33,"column":1},"end":{"line":33,"column":1}},"children":[{"type":"paragraph","children":[{"type":"text","value":"Your dataset receives a ","position":{"start":{"line":33,"column":1},"end":{"line":33,"column":1}},"key":"KvL3W5tZIs"},{"type":"strong","position":{"start":{"line":33,"column":1},"end":{"line":33,"column":1}},"children":[{"type":"text","value":"citable DOI","position":{"start":{"line":33,"column":1},"end":{"line":33,"column":1}},"key":"xhToujUPGj"}],"key":"KikNo2YVA5"},{"type":"text","value":" that can be included in publications","position":{"start":{"line":33,"column":1},"end":{"line":33,"column":1}},"key":"Ao4EO23L7c"}],"key":"ZEqgWRYiRa"}],"key":"prbddNWmq6"},{"type":"listItem","spread":true,"position":{"start":{"line":34,"column":1},"end":{"line":34,"column":1}},"children":[{"type":"paragraph","children":[{"type":"text","value":"Long-term preservation and backups by a trusted, ","position":{"start":{"line":34,"column":1},"end":{"line":34,"column":1}},"key":"lRAo3HJewF"},{"type":"strong","position":{"start":{"line":34,"column":1},"end":{"line":34,"column":1}},"children":[{"type":"text","value":"CoreTrustSeal certified","position":{"start":{"line":34,"column":1},"end":{"line":34,"column":1}},"key":"MU7SimjHCm"}],"key":"yiRmokSNL9"},{"type":"text","value":" repository","position":{"start":{"line":34,"column":1},"end":{"line":34,"column":1}},"key":"x4Jtvg9iR8"}],"key":"GwcEm0d6Fg"}],"key":"Ue5mpvp9eC"},{"type":"listItem","spread":true,"position":{"start":{"line":35,"column":1},"end":{"line":35,"column":1}},"children":[{"type":"paragraph","children":[{"type":"text","value":"Broad discoverability through GDEX search and external indexes (e.g., Google Dataset Search)","position":{"start":{"line":35,"column":1},"end":{"line":35,"column":1}},"key":"HdzoCwygzN"}],"key":"PvzRJkhGnq"}],"key":"mlSlGrIlt5"},{"type":"listItem","spread":true,"position":{"start":{"line":36,"column":1},"end":{"line":36,"column":1}},"children":[{"type":"paragraph","children":[{"type":"text","value":"Compliance with ","position":{"start":{"line":36,"column":1},"end":{"line":36,"column":1}},"key":"oNWcCoyunm"},{"type":"strong","position":{"start":{"line":36,"column":1},"end":{"line":36,"column":1}},"children":[{"type":"text","value":"NSF and journal data sharing requirements","position":{"start":{"line":36,"column":1},"end":{"line":36,"column":1}},"key":"o4dZOS1zPU"}],"key":"QqlB1vMCyo"}],"key":"XLAER9UrXx"}],"key":"UZNa5NluQc"},{"type":"listItem","spread":true,"position":{"start":{"line":37,"column":1},"end":{"line":37,"column":1}},"children":[{"type":"paragraph","children":[{"type":"text","value":"Access to a variety of value added ","position":{"start":{"line":37,"column":1},"end":{"line":37,"column":1}},"key":"QsrwHXCyUk"},{"type":"strong","position":{"start":{"line":37,"column":1},"end":{"line":37,"column":1}},"children":[{"type":"text","value":"services","position":{"start":{"line":37,"column":1},"end":{"line":37,"column":1}},"key":"PbwoRRV35q"}],"key":"CUt3VSoQFA"}],"key":"X3Rjp21Q8S"}],"key":"uXEvDx0lDx"},{"type":"listItem","spread":true,"position":{"start":{"line":38,"column":1},"end":{"line":38,"column":1}},"children":[{"type":"paragraph","children":[{"type":"text","value":"Your data becomes part of a collection used by researchers worldwide","position":{"start":{"line":38,"column":1},"end":{"line":38,"column":1}},"key":"tsVTy26tuc"}],"key":"EN5KXJgMoR"}],"key":"C8OXCCiHBm"}],"key":"mdTTrTrgON"}],"key":"J1VaO3y48o"},{"type":"block","kind":"notebook-content","children":[{"type":"admonition","kind":"tip","children":[{"type":"admonitionTitle","children":[{"type":"text","value":"Tip","key":"esSK4K7aRk"}],"key":"Dp2LYiIxwP"},{"type":"paragraph","position":{"start":{"line":2,"column":1},"end":{"line":2,"column":1}},"children":[{"type":"text","value":"Contact ","position":{"start":{"line":2,"column":1},"end":{"line":2,"column":1}},"key":"DZWTHz3g4v"},{"type":"link","url":"mailto:datahelp@ucar.edu","position":{"start":{"line":2,"column":1},"end":{"line":2,"column":1}},"children":[{"type":"text","value":"datahelp@ucar.edu","position":{"start":{"line":2,"column":1},"end":{"line":2,"column":1}},"key":"xm1wRZtr7j"}],"urlSource":"mailto:datahelp@ucar.edu","key":"JUAp6cdgJs"},{"type":"text","value":" before investing significant effort in data preparation. The GDEX team can confirm your dataset is a good fit and advise on format and metadata requirements.","position":{"start":{"line":2,"column":1},"end":{"line":2,"column":1}},"key":"skjg17IX0I"}],"key":"n84PDhKHuw"}],"key":"RAGPHiXlBJ"}],"key":"znAaiRzv6V"},{"type":"block","kind":"notebook-content","children":[{"type":"heading","depth":2,"position":{"start":{"line":1,"column":1},"end":{"line":1,"column":1}},"children":[{"type":"text","value":"How GDEX Enables Science","position":{"start":{"line":1,"column":1},"end":{"line":1,"column":1}},"key":"bi3WpVKMlS"}],"identifier":"how-gdex-enables-science","label":"How GDEX Enables Science","html_id":"how-gdex-enables-science","implicit":true,"key":"LK3oMvSaWr"},{"type":"paragraph","position":{"start":{"line":3,"column":1},"end":{"line":3,"column":1}},"children":[{"type":"text","value":"GDEX is more than a file repository — it is infrastructure that enables scientific discovery at scale.","position":{"start":{"line":3,"column":1},"end":{"line":3,"column":1}},"key":"JbKhAJCWXY"}],"key":"HZ3Sb0SHf0"},{"type":"heading","depth":3,"position":{"start":{"line":5,"column":1},"end":{"line":5,"column":1}},"children":[{"type":"text","value":"Reproducible Research","position":{"start":{"line":5,"column":1},"end":{"line":5,"column":1}},"key":"C0IQ3irnOe"}],"identifier":"reproducible-research","label":"Reproducible Research","html_id":"reproducible-research","implicit":true,"key":"PU58r41d31"},{"type":"paragraph","position":{"start":{"line":7,"column":1},"end":{"line":7,"column":1}},"children":[{"type":"text","value":"By providing stable, versioned, citable datasets, GDEX makes it possible to reproduce published analyses years after the fact. When a paper cites a GDEX dataset DOI, any researcher in the world can access the exact same data used in that study.","position":{"start":{"line":7,"column":1},"end":{"line":7,"column":1}},"key":"qiFOfBHApj"}],"key":"eBDOAg2THe"},{"type":"heading","depth":3,"position":{"start":{"line":9,"column":1},"end":{"line":9,"column":1}},"children":[{"type":"text","value":"Lowering Barriers to Large-Scale Analysis","position":{"start":{"line":9,"column":1},"end":{"line":9,"column":1}},"key":"J3zQszaVhQ"}],"identifier":"lowering-barriers-to-large-scale-analysis","label":"Lowering Barriers to Large-Scale Analysis","html_id":"lowering-barriers-to-large-scale-analysis","implicit":true,"key":"MvCmJNVGOC"},{"type":"paragraph","position":{"start":{"line":11,"column":1},"end":{"line":11,"column":1}},"children":[{"type":"text","value":"Some of the most scientifically important datasets are also the largest. ERA5 global reanalysis alone spans petabytes. GDEX removes the logistical barriers to working with these datasets by:","position":{"start":{"line":11,"column":1},"end":{"line":11,"column":1}},"key":"v9IvW446t9"}],"key":"p6YFRCINnp"},{"type":"list","ordered":false,"spread":false,"position":{"start":{"line":13,"column":1},"end":{"line":16,"column":1}},"children":[{"type":"listItem","spread":true,"position":{"start":{"line":13,"column":1},"end":{"line":13,"column":1}},"children":[{"type":"paragraph","children":[{"type":"text","value":"Hosting data on infrastructure optimized for high-throughput access","position":{"start":{"line":13,"column":1},"end":{"line":13,"column":1}},"key":"ygYV5o8bwQ"}],"key":"EM898iemDz"}],"key":"zmAAEUmtwG"},{"type":"listItem","spread":true,"position":{"start":{"line":14,"column":1},"end":{"line":14,"column":1}},"children":[{"type":"paragraph","children":[{"type":"text","value":"Providing cloud-optimized formats (Zarr, Kerchunk) that enable streaming analysis without full downloads","position":{"start":{"line":14,"column":1},"end":{"line":14,"column":1}},"key":"OiqP4TLvBm"}],"key":"VEdjhQdt1H"}],"key":"kSOZBi6dIW"},{"type":"listItem","spread":true,"position":{"start":{"line":15,"column":1},"end":{"line":16,"column":1}},"children":[{"type":"paragraph","children":[{"type":"text","value":"Supporting compute-proximate workflows on NSF NCAR HPC systems","position":{"start":{"line":15,"column":1},"end":{"line":15,"column":1}},"key":"UUijgELf6C"}],"key":"g9uwWMNgNh"}],"key":"mZLyLbyTTS"}],"key":"HXZuMCvEjQ"},{"type":"heading","depth":3,"position":{"start":{"line":17,"column":1},"end":{"line":17,"column":1}},"children":[{"type":"text","value":"Enabling Multi-Dataset Science","position":{"start":{"line":17,"column":1},"end":{"line":17,"column":1}},"key":"PptiQgGiG3"}],"identifier":"enabling-multi-dataset-science","label":"Enabling Multi-Dataset Science","html_id":"enabling-multi-dataset-science","implicit":true,"key":"x7mV81ypfn"},{"type":"paragraph","position":{"start":{"line":19,"column":1},"end":{"line":19,"column":1}},"children":[{"type":"text","value":"Because GDEX curates data to common standards, it becomes easier to combine datasets — for example, comparing reanalysis products or merging model output with observations. Consistent metadata and file formats reduce the data wrangling burden and let researchers focus on science.","position":{"start":{"line":19,"column":1},"end":{"line":19,"column":1}},"key":"cxsyo2s5Fs"}],"key":"WjN57h549I"},{"type":"heading","depth":3,"position":{"start":{"line":21,"column":1},"end":{"line":21,"column":1}},"children":[{"type":"text","value":"Supporting Data-Driven Discovery","position":{"start":{"line":21,"column":1},"end":{"line":21,"column":1}},"key":"wHqa8LSiAT"}],"identifier":"supporting-data-driven-discovery","label":"Supporting Data-Driven Discovery","html_id":"supporting-data-driven-discovery","implicit":true,"key":"ggwve0QEeo"},{"type":"paragraph","position":{"start":{"line":23,"column":1},"end":{"line":23,"column":1}},"children":[{"type":"text","value":"The scale and diversity of GDEX collections make them well-suited for emerging methods in geoscience:","position":{"start":{"line":23,"column":1},"end":{"line":23,"column":1}},"key":"nSYE93qwsm"}],"key":"srTEXN5EA8"},{"type":"list","ordered":false,"spread":false,"position":{"start":{"line":25,"column":1},"end":{"line":30,"column":1}},"children":[{"type":"listItem","spread":true,"position":{"start":{"line":25,"column":1},"end":{"line":25,"column":1}},"children":[{"type":"paragraph","children":[{"type":"strong","position":{"start":{"line":25,"column":1},"end":{"line":25,"column":1}},"children":[{"type":"text","value":"Machine learning","position":{"start":{"line":25,"column":1},"end":{"line":25,"column":1}},"key":"wngxOu5VHj"}],"key":"Kq2iEvWt1r"},{"type":"text","value":" applications that require large training datasets","position":{"start":{"line":25,"column":1},"end":{"line":25,"column":1}},"key":"I0UJkRSdS4"}],"key":"xMXgGhMkEd"}],"key":"k6AC15qRty"},{"type":"listItem","spread":true,"position":{"start":{"line":26,"column":1},"end":{"line":26,"column":1}},"children":[{"type":"paragraph","children":[{"type":"strong","position":{"start":{"line":26,"column":1},"end":{"line":26,"column":1}},"children":[{"type":"text","value":"Long-term trend analysis","position":{"start":{"line":26,"column":1},"end":{"line":26,"column":1}},"key":"UpB8ibkgnU"}],"key":"xC7wklVPHa"},{"type":"text","value":" using multi-decadal observational records","position":{"start":{"line":26,"column":1},"end":{"line":26,"column":1}},"key":"TjUu4yye8G"}],"key":"dMI0mDspqh"}],"key":"nWDpYm3999"},{"type":"listItem","spread":true,"position":{"start":{"line":27,"column":1},"end":{"line":27,"column":1}},"children":[{"type":"paragraph","children":[{"type":"strong","position":{"start":{"line":27,"column":1},"end":{"line":27,"column":1}},"children":[{"type":"text","value":"Model evaluation","position":{"start":{"line":27,"column":1},"end":{"line":27,"column":1}},"key":"QXyfSOGzmH"}],"key":"kLvOBq3RoJ"},{"type":"text","value":" comparing simulations against observational benchmarks","position":{"start":{"line":27,"column":1},"end":{"line":27,"column":1}},"key":"zz1ggRCMVw"}],"key":"l97agt4hTQ"}],"key":"mW7O0Ttslo"},{"type":"listItem","spread":true,"position":{"start":{"line":28,"column":1},"end":{"line":30,"column":1}},"children":[{"type":"paragraph","children":[{"type":"strong","position":{"start":{"line":28,"column":1},"end":{"line":28,"column":1}},"children":[{"type":"text","value":"Climate impact studies","position":{"start":{"line":28,"column":1},"end":{"line":28,"column":1}},"key":"LkDQKnSDiF"}],"key":"QcTBPB7AkZ"},{"type":"text","value":" combining atmospheric, oceanic, and land surface data","position":{"start":{"line":28,"column":1},"end":{"line":28,"column":1}},"key":"KkXuBMerkN"}],"key":"ZbcCqAYaFk"}],"key":"p79i1R3G9J"}],"key":"HpQzQkQfgC"}],"key":"iDOzU3RuG0"},{"type":"block","kind":"notebook-content","children":[{"type":"admonition","kind":"seealso","children":[{"type":"admonitionTitle","children":[{"type":"text","value":"See Also","key":"eG4JdMqfvF"}],"key":"IsCG1ZBnn1"},{"type":"paragraph","position":{"start":{"line":2,"column":1},"end":{"line":2,"column":1}},"children":[{"type":"link","url":"/notebooks/gdex-intro/enabling-science","urlSource":"enabling_science","dataUrl":"/notebooks.gdex-intro.enabling-science.json","internal":true,"children":[{"type":"text","value":"Enabling Science","key":"Zxc138cVMT"}],"protocol":"file","key":"NngagFtTb0"},{"type":"text","value":" — a deeper dive into analysis-ready and AI-ready data, cloud-optimized formats, and machine learning workflows.","position":{"start":{"line":2,"column":1},"end":{"line":2,"column":1}},"key":"khWM7kuUV2"}],"key":"EhP53ZUbar"}],"key":"ISJCADiaiA"}],"key":"YKlc3fnJre"},{"type":"block","kind":"notebook-content","children":[{"type":"thematicBreak","position":{"start":{"line":1,"column":1},"end":{"line":1,"column":1}},"key":"L7R4t2cw64"}],"key":"MMJV2Fj3oR"},{"type":"block","kind":"notebook-content","children":[{"type":"heading","depth":2,"position":{"start":{"line":1,"column":1},"end":{"line":1,"column":1}},"children":[{"type":"text","value":"Summary","position":{"start":{"line":1,"column":1},"end":{"line":1,"column":1}},"key":"BnqT4SFNzT"}],"identifier":"summary","label":"Summary","html_id":"summary","implicit":true,"key":"BCqx8wC7iD"},{"type":"paragraph","position":{"start":{"line":3,"column":1},"end":{"line":3,"column":1}},"children":[{"type":"text","value":"NSF NCAR’s Geoscience Data Exchange (GDEX) is a trusted, long-term home for geoscience data — one that serves the research community both as a data archive and as an active platform for scientific discovery.","position":{"start":{"line":3,"column":1},"end":{"line":3,"column":1}},"key":"Hr4OWrsE6Y"}],"key":"bRCkK6tYEm"},{"type":"paragraph","position":{"start":{"line":5,"column":1},"end":{"line":5,"column":1}},"children":[{"type":"text","value":"Key takeaways:","position":{"start":{"line":5,"column":1},"end":{"line":5,"column":1}},"key":"be7iKQ2Ys0"}],"key":"nh9ATDEh2l"},{"type":"list","ordered":false,"spread":false,"position":{"start":{"line":7,"column":1},"end":{"line":11,"column":1}},"children":[{"type":"listItem","spread":true,"position":{"start":{"line":7,"column":1},"end":{"line":7,"column":1}},"children":[{"type":"paragraph","children":[{"type":"strong","position":{"start":{"line":7,"column":1},"end":{"line":7,"column":1}},"children":[{"type":"text","value":"GDEX hosts thousands of datasets","position":{"start":{"line":7,"column":1},"end":{"line":7,"column":1}},"key":"ZcDWPaGfTT"}],"key":"Wz4YPetDwH"},{"type":"text","value":" spanning atmospheric, oceanic, and Earth system science, from century-long observational records to petabyte-scale reanalysis products","position":{"start":{"line":7,"column":1},"end":{"line":7,"column":1}},"key":"mBoRxqHFut"}],"key":"RIt3XkCP1S"}],"key":"OJxBH5XUSr"},{"type":"listItem","spread":true,"position":{"start":{"line":8,"column":1},"end":{"line":8,"column":1}},"children":[{"type":"paragraph","children":[{"type":"strong","position":{"start":{"line":8,"column":1},"end":{"line":8,"column":1}},"children":[{"type":"text","value":"Multiple access pathways","position":{"start":{"line":8,"column":1},"end":{"line":8,"column":1}},"key":"GSDY62G27k"}],"key":"S1qBlekh8d"},{"type":"text","value":" — web download, Globus, OPeNDAP, and cloud streaming — ensure data is reachable wherever researchers work","position":{"start":{"line":8,"column":1},"end":{"line":8,"column":1}},"key":"unAtnA1D2T"}],"key":"Pu7EdcIYlN"}],"key":"wrrfbEaMtk"},{"type":"listItem","spread":true,"position":{"start":{"line":9,"column":1},"end":{"line":9,"column":1}},"children":[{"type":"paragraph","children":[{"type":"strong","position":{"start":{"line":9,"column":1},"end":{"line":9,"column":1}},"children":[{"type":"text","value":"Data submission is open to the community","position":{"start":{"line":9,"column":1},"end":{"line":9,"column":1}},"key":"etsqZeiWHU"}],"key":"BUpXrFORXa"},{"type":"text","value":": archiving your data with GDEX provides a citable DOI, long-term preservation, and broad discoverability","position":{"start":{"line":9,"column":1},"end":{"line":9,"column":1}},"key":"SFG1zhk5XT"}],"key":"gl6TfprSpi"}],"key":"ArcTDY4XcL"},{"type":"listItem","spread":true,"position":{"start":{"line":10,"column":1},"end":{"line":11,"column":1}},"children":[{"type":"paragraph","children":[{"type":"strong","position":{"start":{"line":10,"column":1},"end":{"line":10,"column":1}},"children":[{"type":"text","value":"GDEX enables science","position":{"start":{"line":10,"column":1},"end":{"line":10,"column":1}},"key":"gZ2LKFmdK6"}],"key":"LhRBpzwNd4"},{"type":"text","value":" by lowering barriers to large-scale data access, supporting reproducibility, and providing infrastructure for modern data-driven workflows","position":{"start":{"line":10,"column":1},"end":{"line":10,"column":1}},"key":"z2VZCG6jxk"}],"key":"y0N0bXu2ZT"}],"key":"buJ0QGKGVD"}],"key":"YbgEFhuSwq"},{"type":"paragraph","position":{"start":{"line":12,"column":1},"end":{"line":12,"column":1}},"children":[{"type":"text","value":"The notebooks in this cookbook demonstrate hands-on use of GDEX data, from basic access patterns to cloud-native analysis at scale.","position":{"start":{"line":12,"column":1},"end":{"line":12,"column":1}},"key":"MsnYdALZhA"}],"key":"jj6iMJ46ey"}],"key":"RLHHmZdGWf"},{"type":"block","kind":"notebook-content","children":[{"type":"heading","depth":2,"position":{"start":{"line":1,"column":1},"end":{"line":1,"column":1}},"children":[{"type":"text","value":"Getting Help","position":{"start":{"line":1,"column":1},"end":{"line":1,"column":1}},"key":"xiw1S4iD4y"}],"identifier":"getting-help","label":"Getting Help","html_id":"getting-help","implicit":true,"key":"vFRLMuWYny"},{"type":"paragraph","position":{"start":{"line":3,"column":1},"end":{"line":3,"column":1}},"children":[{"type":"text","value":"The GDEX team provides direct support for data access, discovery, and submission questions.","position":{"start":{"line":3,"column":1},"end":{"line":3,"column":1}},"key":"jZcvbOF5TU"}],"key":"uVCgX3hf31"},{"type":"heading","depth":3,"position":{"start":{"line":5,"column":1},"end":{"line":5,"column":1}},"children":[{"type":"text","value":"Data Help Desk","position":{"start":{"line":5,"column":1},"end":{"line":5,"column":1}},"key":"hsXTnewz7v"}],"identifier":"data-help-desk","label":"Data Help Desk","html_id":"data-help-desk","implicit":true,"key":"kvPXtBHHDN"},{"type":"paragraph","position":{"start":{"line":7,"column":1},"end":{"line":7,"column":1}},"children":[{"type":"text","value":"The primary support channel is the ","position":{"start":{"line":7,"column":1},"end":{"line":7,"column":1}},"key":"miqNkLcHX9"},{"type":"strong","position":{"start":{"line":7,"column":1},"end":{"line":7,"column":1}},"children":[{"type":"text","value":"GDEX Data Help Desk","position":{"start":{"line":7,"column":1},"end":{"line":7,"column":1}},"key":"EnCYwhKTOy"}],"key":"J8qBnOwoBP"},{"type":"text","value":":","position":{"start":{"line":7,"column":1},"end":{"line":7,"column":1}},"key":"eo57v1Tk0b"}],"key":"oBmmvcz0C3"},{"type":"list","ordered":false,"spread":false,"position":{"start":{"line":9,"column":1},"end":{"line":12,"column":1}},"children":[{"type":"listItem","spread":true,"position":{"start":{"line":9,"column":1},"end":{"line":9,"column":1}},"children":[{"type":"paragraph","children":[{"type":"strong","position":{"start":{"line":9,"column":1},"end":{"line":9,"column":1}},"children":[{"type":"text","value":"Email","position":{"start":{"line":9,"column":1},"end":{"line":9,"column":1}},"key":"UVzkXe3sje"}],"key":"aPqaSpMs9u"},{"type":"text","value":": ","position":{"start":{"line":9,"column":1},"end":{"line":9,"column":1}},"key":"HbKPCfQhA6"},{"type":"link","url":"mailto:datahelp@ucar.edu","position":{"start":{"line":9,"column":1},"end":{"line":9,"column":1}},"children":[{"type":"text","value":"datahelp@ucar.edu","position":{"start":{"line":9,"column":1},"end":{"line":9,"column":1}},"key":"FtvKi70iUW"}],"urlSource":"mailto:datahelp@ucar.edu","key":"QZtnCT4FhB"}],"key":"dGw8rsc3TX"}],"key":"ro2Jd129qB"},{"type":"listItem","spread":true,"position":{"start":{"line":10,"column":1},"end":{"line":10,"column":1}},"children":[{"type":"paragraph","children":[{"type":"strong","position":{"start":{"line":10,"column":1},"end":{"line":10,"column":1}},"children":[{"type":"text","value":"Response time","position":{"start":{"line":10,"column":1},"end":{"line":10,"column":1}},"key":"FBUILgkrGG"}],"key":"zolPs6roKk"},{"type":"text","value":": typically 1–2 business days","position":{"start":{"line":10,"column":1},"end":{"line":10,"column":1}},"key":"j4F5kZ9W6Z"}],"key":"VSf1ByjwIB"}],"key":"E6noY9AxyL"},{"type":"listItem","spread":true,"position":{"start":{"line":11,"column":1},"end":{"line":12,"column":1}},"children":[{"type":"paragraph","children":[{"type":"strong","position":{"start":{"line":11,"column":1},"end":{"line":11,"column":1}},"children":[{"type":"text","value":"Best for","position":{"start":{"line":11,"column":1},"end":{"line":11,"column":1}},"key":"pd7on882Vz"}],"key":"mGf2nYMebq"},{"type":"text","value":": data access problems, subsetting questions, format guidance, submission inquiries, and anything not covered by documentation","position":{"start":{"line":11,"column":1},"end":{"line":11,"column":1}},"key":"PsSNkNn3U2"}],"key":"L7I7IqHW3r"}],"key":"YqE5cx5mU0"}],"key":"spD1YOIu9C"},{"type":"paragraph","position":{"start":{"line":13,"column":1},"end":{"line":13,"column":1}},"children":[{"type":"text","value":"When emailing, include the dataset identifier (e.g., ","position":{"start":{"line":13,"column":1},"end":{"line":13,"column":1}},"key":"XQdHZ2CaL5"},{"type":"inlineCode","value":"ds083.2","position":{"start":{"line":13,"column":1},"end":{"line":13,"column":1}},"key":"OdHDLYZ7vK"},{"type":"text","value":") and a description of what you were trying to do — this significantly speeds up the response.","position":{"start":{"line":13,"column":1},"end":{"line":13,"column":1}},"key":"uOedxZUXxy"}],"key":"ExLu6hCWXO"},{"type":"heading","depth":3,"position":{"start":{"line":15,"column":1},"end":{"line":15,"column":1}},"children":[{"type":"text","value":"Common Questions","position":{"start":{"line":15,"column":1},"end":{"line":15,"column":1}},"key":"ll03A2A2WT"}],"identifier":"common-questions","label":"Common Questions","html_id":"common-questions","implicit":true,"key":"qxak4XwRO5"},{"type":"table","position":{"start":{"line":17,"column":1},"end":{"line":24,"column":1}},"children":[{"type":"tableRow","position":{"start":{"line":17,"column":1},"end":{"line":17,"column":1}},"children":[{"type":"tableCell","header":true,"position":{"start":{"line":17,"column":1},"end":{"line":17,"column":1}},"children":[{"type":"text","value":"Question","position":{"start":{"line":17,"column":1},"end":{"line":17,"column":1}},"key":"A0vcFFQ8J6"}],"key":"SeCgNk5yIE"},{"type":"tableCell","header":true,"position":{"start":{"line":17,"column":1},"end":{"line":17,"column":1}},"children":[{"type":"text","value":"Where to look first","position":{"start":{"line":17,"column":1},"end":{"line":17,"column":1}},"key":"mfgcHIUBYe"}],"key":"xpDDeV6kt4"}],"key":"d3jxAW6oMB"},{"type":"tableRow","position":{"start":{"line":19,"column":1},"end":{"line":19,"column":1}},"children":[{"type":"tableCell","position":{"start":{"line":19,"column":1},"end":{"line":19,"column":1}},"children":[{"type":"text","value":"I can’t find a dataset","position":{"start":{"line":19,"column":1},"end":{"line":19,"column":1}},"key":"uQgdHszr6z"}],"key":"MQdH701xas"},{"type":"tableCell","position":{"start":{"line":19,"column":1},"end":{"line":19,"column":1}},"children":[{"type":"link","url":"https://gdex.ucar.edu/gsearch/dataset-search/","position":{"start":{"line":19,"column":1},"end":{"line":19,"column":1}},"children":[{"type":"text","value":"Dataset search","position":{"start":{"line":19,"column":1},"end":{"line":19,"column":1}},"key":"pH98fAnNo4"}],"urlSource":"https://gdex.ucar.edu/gsearch/dataset-search/","key":"QFvaQ5Q8w2"},{"type":"text","value":" — try broader terms or filtering by variable","position":{"start":{"line":19,"column":1},"end":{"line":19,"column":1}},"key":"kaFaqn9TWc"}],"key":"Kj3436nXPA"}],"key":"dxdQv3U9Wx"},{"type":"tableRow","position":{"start":{"line":20,"column":1},"end":{"line":20,"column":1}},"children":[{"type":"tableCell","position":{"start":{"line":20,"column":1},"end":{"line":20,"column":1}},"children":[{"type":"text","value":"I need access to a restricted dataset","position":{"start":{"line":20,"column":1},"end":{"line":20,"column":1}},"key":"atJCd0tbIU"}],"key":"uXVSfF3PRq"},{"type":"tableCell","position":{"start":{"line":20,"column":1},"end":{"line":20,"column":1}},"children":[{"type":"text","value":"Check the dataset page for access instructions, or email the help desk","position":{"start":{"line":20,"column":1},"end":{"line":20,"column":1}},"key":"liN8KlBiEn"}],"key":"Kavy3GvoTO"}],"key":"p4gml8q9Cl"},{"type":"tableRow","position":{"start":{"line":21,"column":1},"end":{"line":21,"column":1}},"children":[{"type":"tableCell","position":{"start":{"line":21,"column":1},"end":{"line":21,"column":1}},"children":[{"type":"text","value":"My download failed or is very slow","position":{"start":{"line":21,"column":1},"end":{"line":21,"column":1}},"key":"Gnsri4FGCK"}],"key":"TH0P91vfLD"},{"type":"tableCell","position":{"start":{"line":21,"column":1},"end":{"line":21,"column":1}},"children":[{"type":"text","value":"Try ","position":{"start":{"line":21,"column":1},"end":{"line":21,"column":1}},"key":"UI3XGsKzwE"},{"type":"link","url":"https://www.globus.org/","position":{"start":{"line":21,"column":1},"end":{"line":21,"column":1}},"children":[{"type":"text","value":"Globus","position":{"start":{"line":21,"column":1},"end":{"line":21,"column":1}},"key":"RQhczpXQxt"}],"urlSource":"https://www.globus.org/","key":"FuUPoyQdtY"},{"type":"text","value":" for large transfers, or email the help desk","position":{"start":{"line":21,"column":1},"end":{"line":21,"column":1}},"key":"TGcszc5afU"}],"key":"gNDSVW0w4O"}],"key":"mkXN0Cc4RH"},{"type":"tableRow","position":{"start":{"line":22,"column":1},"end":{"line":22,"column":1}},"children":[{"type":"tableCell","position":{"start":{"line":22,"column":1},"end":{"line":22,"column":1}},"children":[{"type":"text","value":"I want to submit data to GDEX","position":{"start":{"line":22,"column":1},"end":{"line":22,"column":1}},"key":"SDGoXy056G"}],"key":"hfZblFa3IN"},{"type":"tableCell","position":{"start":{"line":22,"column":1},"end":{"line":22,"column":1}},"children":[{"type":"text","value":"See the ","position":{"start":{"line":22,"column":1},"end":{"line":22,"column":1}},"key":"thrCzSLwiI"},{"type":"link","url":"https://gdex.ucar.edu/resources/submit-data/","position":{"start":{"line":22,"column":1},"end":{"line":22,"column":1}},"children":[{"type":"text","value":"submission page","position":{"start":{"line":22,"column":1},"end":{"line":22,"column":1}},"key":"FkkARxT66R"}],"urlSource":"https://gdex.ucar.edu/resources/submit-data/","key":"FVcZQFKV4L"},{"type":"text","value":" or the Data Submission notebook in this cookbook","position":{"start":{"line":22,"column":1},"end":{"line":22,"column":1}},"key":"zElWIzy12e"}],"key":"Ntg6bRnm0k"}],"key":"MfK13cG0ek"},{"type":"tableRow","position":{"start":{"line":23,"column":1},"end":{"line":23,"column":1}},"children":[{"type":"tableCell","position":{"start":{"line":23,"column":1},"end":{"line":23,"column":1}},"children":[{"type":"text","value":"I need help with a specific Python workflow","position":{"start":{"line":23,"column":1},"end":{"line":23,"column":1}},"key":"ykSxsYUfxc"}],"key":"j9apk6dNKD"},{"type":"tableCell","position":{"start":{"line":23,"column":1},"end":{"line":23,"column":1}},"children":[{"type":"text","value":"Browse the service notebooks in this cookbook","position":{"start":{"line":23,"column":1},"end":{"line":23,"column":1}},"key":"zTlK8g2QDH"}],"key":"d3FH8bZGLO"}],"key":"ytGogYaC6H"},{"type":"tableRow","position":{"start":{"line":24,"column":1},"end":{"line":24,"column":1}},"children":[{"type":"tableCell","position":{"start":{"line":24,"column":1},"end":{"line":24,"column":1}},"children":[{"type":"text","value":"A dataset seems incorrect or has a quality issue","position":{"start":{"line":24,"column":1},"end":{"line":24,"column":1}},"key":"ldz1CR58kd"}],"key":"Y7JJVHiwij"},{"type":"tableCell","position":{"start":{"line":24,"column":1},"end":{"line":24,"column":1}},"children":[{"type":"text","value":"Email the help desk with the dataset ID and a description of the issue","position":{"start":{"line":24,"column":1},"end":{"line":24,"column":1}},"key":"Vltful0gRD"}],"key":"HOAdoXCz2R"}],"key":"O0wOAjHLZx"}],"key":"pVEqRlOVmu"},{"type":"heading","depth":3,"position":{"start":{"line":26,"column":1},"end":{"line":26,"column":1}},"children":[{"type":"text","value":"Documentation","position":{"start":{"line":26,"column":1},"end":{"line":26,"column":1}},"key":"Uwlo3FoO0Y"}],"identifier":"documentation","label":"Documentation","html_id":"documentation","implicit":true,"key":"WnLWjCwqWm"},{"type":"list","ordered":false,"spread":false,"position":{"start":{"line":28,"column":1},"end":{"line":32,"column":1}},"children":[{"type":"listItem","spread":true,"position":{"start":{"line":28,"column":1},"end":{"line":28,"column":1}},"children":[{"type":"paragraph","children":[{"type":"strong","position":{"start":{"line":28,"column":1},"end":{"line":28,"column":1}},"children":[{"type":"text","value":"GDEX user documentation","position":{"start":{"line":28,"column":1},"end":{"line":28,"column":1}},"key":"PyKhufavmv"}],"key":"qKEX5lgIpD"},{"type":"text","value":": ","position":{"start":{"line":28,"column":1},"end":{"line":28,"column":1}},"key":"fep1uClg2m"},{"type":"link","url":"https://gdex.ucar.edu","position":{"start":{"line":28,"column":1},"end":{"line":28,"column":1}},"children":[{"type":"text","value":"gdex.ucar.edu","position":{"start":{"line":28,"column":1},"end":{"line":28,"column":1}},"key":"q27051jSis"}],"urlSource":"https://gdex.ucar.edu","key":"q5P8fk898y"},{"type":"text","value":" — dataset-specific documentation is linked from each dataset’s landing page","position":{"start":{"line":28,"column":1},"end":{"line":28,"column":1}},"key":"VIKUc2uPkt"}],"key":"IMkztFNzYk"}],"key":"n7meNvu7G2"},{"type":"listItem","spread":true,"position":{"start":{"line":29,"column":1},"end":{"line":29,"column":1}},"children":[{"type":"paragraph","children":[{"type":"strong","position":{"start":{"line":29,"column":1},"end":{"line":29,"column":1}},"children":[{"type":"text","value":"rdams-client","position":{"start":{"line":29,"column":1},"end":{"line":29,"column":1}},"key":"c68ka2jzyP"}],"key":"mHW8k9R6MV"},{"type":"text","value":" (Python API client): ","position":{"start":{"line":29,"column":1},"end":{"line":29,"column":1}},"key":"pSspM7Fnil"},{"type":"link","url":"https://github.com/NCAR/rdams-client","position":{"start":{"line":29,"column":1},"end":{"line":29,"column":1}},"children":[{"type":"text","value":"github​.com​/NCAR​/rdams​-client","position":{"start":{"line":29,"column":1},"end":{"line":29,"column":1}},"key":"r1eX79dwA8"}],"urlSource":"https://github.com/NCAR/rdams-client","error":true,"key":"fI7l7L4CEW"}],"key":"OQy83EMurC"}],"key":"Yam4grwD1X"},{"type":"listItem","spread":true,"position":{"start":{"line":30,"column":1},"end":{"line":30,"column":1}},"children":[{"type":"paragraph","children":[{"type":"strong","position":{"start":{"line":30,"column":1},"end":{"line":30,"column":1}},"children":[{"type":"text","value":"Siphon","position":{"start":{"line":30,"column":1},"end":{"line":30,"column":1}},"key":"mk5YJN5GW4"}],"key":"eqVc3uxQBj"},{"type":"text","value":" (THREDDS/TDS access): ","position":{"start":{"line":30,"column":1},"end":{"line":30,"column":1}},"key":"NfMCMRkPbI"},{"type":"link","url":"https://unidata.github.io/siphon/","position":{"start":{"line":30,"column":1},"end":{"line":30,"column":1}},"children":[{"type":"text","value":"unidata​.github​.io​/siphon","position":{"start":{"line":30,"column":1},"end":{"line":30,"column":1}},"key":"rLkKbMbRza"}],"urlSource":"https://unidata.github.io/siphon/","key":"SEbYY6snG0"}],"key":"dWMR7XLpJJ"}],"key":"mKCTjJwSmA"},{"type":"listItem","spread":true,"position":{"start":{"line":31,"column":1},"end":{"line":32,"column":1}},"children":[{"type":"paragraph","children":[{"type":"strong","position":{"start":{"line":31,"column":1},"end":{"line":31,"column":1}},"children":[{"type":"text","value":"CF Conventions","position":{"start":{"line":31,"column":1},"end":{"line":31,"column":1}},"key":"IR302jOWZA"}],"key":"JgQ8A5BChe"},{"type":"text","value":": ","position":{"start":{"line":31,"column":1},"end":{"line":31,"column":1}},"key":"JNLxe5Lgw3"},{"type":"link","url":"http://cfconventions.org/","position":{"start":{"line":31,"column":1},"end":{"line":31,"column":1}},"children":[{"type":"text","value":"cfconventions.org","position":{"start":{"line":31,"column":1},"end":{"line":31,"column":1}},"key":"BgPbnRGJOi"}],"urlSource":"http://cfconventions.org/","key":"ya6h8JeI9I"},{"type":"text","value":" — variable naming and metadata standards used across GDEX datasets","position":{"start":{"line":31,"column":1},"end":{"line":31,"column":1}},"key":"rMfqbG7fgD"}],"key":"n1l5Qom6U1"}],"key":"sXJFn6ATnn"}],"key":"uQmee9bieQ"},{"type":"heading","depth":3,"position":{"start":{"line":33,"column":1},"end":{"line":33,"column":1}},"children":[{"type":"text","value":"Cookbook Issues and Contributions","position":{"start":{"line":33,"column":1},"end":{"line":33,"column":1}},"key":"PWjCoqkm9Q"}],"identifier":"cookbook-issues-and-contributions","label":"Cookbook Issues and Contributions","html_id":"cookbook-issues-and-contributions","implicit":true,"key":"NwjbhRGSAp"},{"type":"paragraph","position":{"start":{"line":35,"column":1},"end":{"line":35,"column":1}},"children":[{"type":"text","value":"If you find an error in this cookbook or want to suggest a new example:","position":{"start":{"line":35,"column":1},"end":{"line":35,"column":1}},"key":"vNS9EmoD5Y"}],"key":"foH2Yd5lK7"},{"type":"list","ordered":false,"spread":false,"position":{"start":{"line":37,"column":1},"end":{"line":38,"column":1}},"children":[{"type":"listItem","spread":true,"position":{"start":{"line":37,"column":1},"end":{"line":37,"column":1}},"children":[{"type":"paragraph","children":[{"type":"text","value":"Open an issue or pull request on the ","position":{"start":{"line":37,"column":1},"end":{"line":37,"column":1}},"key":"NK30t1pyrA"},{"type":"link","url":"https://github.com/projectpythia/gdex-cookbook","position":{"start":{"line":37,"column":1},"end":{"line":37,"column":1}},"children":[{"type":"text","value":"cookbook GitHub repository","position":{"start":{"line":37,"column":1},"end":{"line":37,"column":1}},"key":"SYVDXfTKTU"}],"urlSource":"https://github.com/projectpythia/gdex-cookbook","error":true,"key":"Vq0NRMrvMZ"}],"key":"dFhdF2kDZB"}],"key":"J15X9OUSLu"},{"type":"listItem","spread":true,"position":{"start":{"line":38,"column":1},"end":{"line":38,"column":1}},"children":[{"type":"paragraph","children":[{"type":"text","value":"Contributions are welcome — see the repository README for guidelines","position":{"start":{"line":38,"column":1},"end":{"line":38,"column":1}},"key":"TUjl9ZmiAJ"}],"key":"k6NSdpJD2S"}],"key":"FF5SBokUmJ"}],"key":"DDE6Dfx6R0"}],"key":"JY0yR1rtQ3"},{"type":"block","kind":"notebook-content","children":[{"type":"heading","depth":2,"position":{"start":{"line":1,"column":1},"end":{"line":1,"column":1}},"children":[{"type":"text","value":"Resources and References","position":{"start":{"line":1,"column":1},"end":{"line":1,"column":1}},"key":"gCDoedULWN"}],"identifier":"resources-and-references","label":"Resources and References","html_id":"resources-and-references","implicit":true,"key":"vNhN92BhPv"},{"type":"list","ordered":false,"spread":false,"position":{"start":{"line":3,"column":1},"end":{"line":9,"column":1}},"children":[{"type":"listItem","spread":true,"position":{"start":{"line":3,"column":1},"end":{"line":3,"column":1}},"children":[{"type":"paragraph","children":[{"type":"strong","position":{"start":{"line":3,"column":1},"end":{"line":3,"column":1}},"children":[{"type":"text","value":"GDEX Portal","position":{"start":{"line":3,"column":1},"end":{"line":3,"column":1}},"key":"UjjiCTPjd4"}],"key":"K1vqxNJoZE"},{"type":"text","value":": ","position":{"start":{"line":3,"column":1},"end":{"line":3,"column":1}},"key":"oa2eHlhFsT"},{"type":"link","url":"https://gdex.ucar.edu","position":{"start":{"line":3,"column":1},"end":{"line":3,"column":1}},"children":[{"type":"text","value":"gdex.ucar.edu","position":{"start":{"line":3,"column":1},"end":{"line":3,"column":1}},"key":"yqjULULYkA"}],"urlSource":"https://gdex.ucar.edu","key":"g9EpDntvOv"}],"key":"TYWLiDKjMt"}],"key":"MqUskT3OE4"},{"type":"listItem","spread":true,"position":{"start":{"line":4,"column":1},"end":{"line":4,"column":1}},"children":[{"type":"paragraph","children":[{"type":"strong","position":{"start":{"line":4,"column":1},"end":{"line":4,"column":1}},"children":[{"type":"text","value":"Dataset Search","position":{"start":{"line":4,"column":1},"end":{"line":4,"column":1}},"key":"xxpPS47Hm3"}],"key":"u09u6eRtSD"},{"type":"text","value":": ","position":{"start":{"line":4,"column":1},"end":{"line":4,"column":1}},"key":"GQrmfMyClj"},{"type":"link","url":"https://gdex.ucar.edu/gsearch/dataset-search/","position":{"start":{"line":4,"column":1},"end":{"line":4,"column":1}},"children":[{"type":"text","value":"gdex​.ucar​.edu​/gsearch​/dataset​-search","position":{"start":{"line":4,"column":1},"end":{"line":4,"column":1}},"key":"PsSzOxUr0f"}],"urlSource":"https://gdex.ucar.edu/gsearch/dataset-search/","key":"U76Ye7XNfI"}],"key":"uOcMHedC0M"}],"key":"s21c9S4kos"},{"type":"listItem","spread":true,"position":{"start":{"line":5,"column":1},"end":{"line":5,"column":1}},"children":[{"type":"paragraph","children":[{"type":"strong","position":{"start":{"line":5,"column":1},"end":{"line":5,"column":1}},"children":[{"type":"text","value":"Data Help Desk","position":{"start":{"line":5,"column":1},"end":{"line":5,"column":1}},"key":"aNPeFNM02h"}],"key":"iRJSanFdPd"},{"type":"text","value":": ","position":{"start":{"line":5,"column":1},"end":{"line":5,"column":1}},"key":"ueIRj6if2F"},{"type":"link","url":"mailto:datahelp@ucar.edu","position":{"start":{"line":5,"column":1},"end":{"line":5,"column":1}},"children":[{"type":"text","value":"datahelp@ucar.edu","position":{"start":{"line":5,"column":1},"end":{"line":5,"column":1}},"key":"xvnOf0XaST"}],"urlSource":"mailto:datahelp@ucar.edu","key":"K55ObkzJpX"},{"type":"text","value":" — for data access questions, submission inquiries, or general support","position":{"start":{"line":5,"column":1},"end":{"line":5,"column":1}},"key":"CWtt9JsI2V"}],"key":"gQTOIxK29W"}],"key":"mhfb59pkPt"},{"type":"listItem","spread":true,"position":{"start":{"line":6,"column":1},"end":{"line":6,"column":1}},"children":[{"type":"paragraph","children":[{"type":"strong","position":{"start":{"line":6,"column":1},"end":{"line":6,"column":1}},"children":[{"type":"text","value":"Globus for Data Transfer","position":{"start":{"line":6,"column":1},"end":{"line":6,"column":1}},"key":"TPHDFay2E4"}],"key":"t5gNKNBUna"},{"type":"text","value":": ","position":{"start":{"line":6,"column":1},"end":{"line":6,"column":1}},"key":"x1T6AO9Hpw"},{"type":"link","url":"https://www.globus.org","position":{"start":{"line":6,"column":1},"end":{"line":6,"column":1}},"children":[{"type":"text","value":"globus.org","position":{"start":{"line":6,"column":1},"end":{"line":6,"column":1}},"key":"Kkt6YuGGVC"}],"urlSource":"https://www.globus.org","key":"Zk0SEgtH9j"},{"type":"text","value":" — recommended for bulk transfers","position":{"start":{"line":6,"column":1},"end":{"line":6,"column":1}},"key":"VVWkKLjGlA"}],"key":"kmtwHW20Jf"}],"key":"uRn5oX7Q5y"},{"type":"listItem","spread":true,"position":{"start":{"line":7,"column":1},"end":{"line":7,"column":1}},"children":[{"type":"paragraph","children":[{"type":"strong","position":{"start":{"line":7,"column":1},"end":{"line":7,"column":1}},"children":[{"type":"text","value":"CF Conventions","position":{"start":{"line":7,"column":1},"end":{"line":7,"column":1}},"key":"jbO9dLifXX"}],"key":"nnVu3ub5OU"},{"type":"text","value":": ","position":{"start":{"line":7,"column":1},"end":{"line":7,"column":1}},"key":"tFSBDq0ZRz"},{"type":"link","url":"http://cfconventions.org/","position":{"start":{"line":7,"column":1},"end":{"line":7,"column":1}},"children":[{"type":"text","value":"cfconventions.org","position":{"start":{"line":7,"column":1},"end":{"line":7,"column":1}},"key":"M9OvoS5HeH"}],"urlSource":"http://cfconventions.org/","key":"xaA7uOiHai"},{"type":"text","value":" — metadata standards used by many GDEX datasets","position":{"start":{"line":7,"column":1},"end":{"line":7,"column":1}},"key":"wZswDSJcVc"}],"key":"aQr4zIcPUi"}],"key":"tNKkCycDGQ"},{"type":"listItem","spread":true,"position":{"start":{"line":8,"column":1},"end":{"line":8,"column":1}},"children":[{"type":"paragraph","children":[{"type":"strong","position":{"start":{"line":8,"column":1},"end":{"line":8,"column":1}},"children":[{"type":"text","value":"Zarr Documentation","position":{"start":{"line":8,"column":1},"end":{"line":8,"column":1}},"key":"ZTWtBdhzPX"}],"key":"EdQCK0iaUd"},{"type":"text","value":": ","position":{"start":{"line":8,"column":1},"end":{"line":8,"column":1}},"key":"nwrHw6Vlc6"},{"type":"link","url":"https://zarr.dev","position":{"start":{"line":8,"column":1},"end":{"line":8,"column":1}},"children":[{"type":"text","value":"zarr.dev","position":{"start":{"line":8,"column":1},"end":{"line":8,"column":1}},"key":"WRizY1nq6B"}],"urlSource":"https://zarr.dev","key":"PIz4MuvrWK"},{"type":"text","value":" — cloud-native array format used for streaming access","position":{"start":{"line":8,"column":1},"end":{"line":8,"column":1}},"key":"ZhUcjTXO6K"}],"key":"odv7D1bsxA"}],"key":"O2rrWMJTW7"},{"type":"listItem","spread":true,"position":{"start":{"line":9,"column":1},"end":{"line":9,"column":1}},"children":[{"type":"paragraph","children":[{"type":"strong","position":{"start":{"line":9,"column":1},"end":{"line":9,"column":1}},"children":[{"type":"text","value":"Kerchunk","position":{"start":{"line":9,"column":1},"end":{"line":9,"column":1}},"key":"m02Cjp7ypB"}],"key":"XUWE9APWSA"},{"type":"text","value":": ","position":{"start":{"line":9,"column":1},"end":{"line":9,"column":1}},"key":"atDbSdss0P"},{"type":"link","url":"https://fsspec.github.io/kerchunk/","position":{"start":{"line":9,"column":1},"end":{"line":9,"column":1}},"children":[{"type":"text","value":"fsspec​.github​.io​/kerchunk","position":{"start":{"line":9,"column":1},"end":{"line":9,"column":1}},"key":"G06O2PcDHr"}],"urlSource":"https://fsspec.github.io/kerchunk/","key":"Xu2pRlR181"},{"type":"text","value":" — virtual metadata for remote Grib/NetCDF access","position":{"start":{"line":9,"column":1},"end":{"line":9,"column":1}},"key":"esGnb4Ho8z"}],"key":"in8gKKt19D"}],"key":"orckL2w3nA"}],"key":"hWeUVPwyGA"}],"key":"FUmg3EHfNg"}],"key":"RoPtAwYCGN"},"references":{"cite":{"order":[],"data":{}}},"footer":{"navigation":{"prev":{"title":"How to Cite This Cookbook","url":"/notebooks/how-to-cite","group":"Preamble"},"next":{"title":"GDEX Services","url":"/notebooks/gdex-intro/services","group":"GDEX Introduction"}}},"domain":"http://localhost:3000"}